{"baseBpm":120,"musics":[{"bpm":120,"baseBeats":0.25,"scores":["UVX,UV,UVXY,TUWX,UVY,UV,UVX,TUWY,UVX,UV,UVY,TUV,UVY,UV,UVY,TUVY,VWXY,V,5<V>,VWX,UY,V,V,VX,V,VWXY,U,U,U,VX,V,U,V,5<V>,V,5<V>,VX,V,VWXY,U,U,UY,U,V,5<V>,U,VX,V,V,VY,VW,V,VXY,VWX,U,VY,V,U,VX,UVY,VWXY,VX,UWX,V,5<V>,V,5<V>,VX,UWY,V,5<V>,UY,V,5<V>,V,5<V>,V,5<V>,VXY,UWX,VX,V,VWXY,VWX,VW,UW,V,5<V>,UY,V,5<V>,UY,V,5<V>,VX,VWY,VX,VWX,UX,VX,V,VW,V,UVX,V,5<V>,V,5<V>,V,5<V>,UY,VX,UW,UX,VX,VWX,V,UY,VX,UW,VY,VX;","f[P],(#g1.#g2)[LMP],UV,(c1.f1.f2)[LMOP],TUWX,(f.c2.c3)[LMP],UWXY,c1[P],(f1.f2)[LMO],TUWY,(f.#d2.#d3)[LMO],UWXY,(c1.#a1)[P],#a2[LMP],TUWXY,f[P],(c2.c3)[LMP],UWXY,(c1.f1)[P],f2[LMP],TUWXY,F-1[P],(f.#g1)[P],#g2[MNOP],(F-1.f)[MP],WXY,(F-1.f)[MO],W,(F-1.f.f1.f2)[LP],F-1[P],f[NOP],V,(F-1.f)[MO],WX,F-1[P],f[MP],WXY,(F-1.f)[MO],WX,(F-1.f.c2.c3)[L],(F-1.f)[MO],WX,(F-1.f)[MO],WXY,F-1[P],(f.f1.f2)[L],(F-1.f)[MP],WXY,(F-1.f)[MP],WXY,(F-1.f)[MO],WXY,(F-1.f)[MP],WXY,(F-1.f.#d2.#d3)[L],(F-1.f)[MO],WX,(F-1.f)[MO],WXY,(F-1.f.#a1.#a2)[L],(F-1.f)[MP],WXY,(F-1.f)[MO],WX,(F-1.f)[MO],WXY,(F-1.f)[MP],V,F-1[P],(f.c2.c3)[MN],f[OP],F-1[MP],WXY,(F-1.f)[MP],WY,(F-1.f.f1.f2)[L],F-1[P],f[M],V,(F-1.f)[L],(F-1.f)[MO],UWXY,(F-2.F-1)[P],(#g.c1)[P],(f1.#g1)[MNOP],(F-1.#g.c1.f1.#g1)[MO],WX,(F-1.#g.c1.f1)[P],#g1[M],WXY,(F-2.F-1)[P],(#g.c1.f1.#g1)[MP],WX,F-1[P],(#g.c1)[P],(f1.#g1)[M],W,#g[P],(c1.f1.#g1)[P],F-1[MO],WY,(#g.c1.f1.#g1)[O],(F-2.F-1)[NOP],WXY,#g[P],c1[P],(F-2.f1.#g1)[P],F-1[NO],WXY,(#G-1.#g)[P],(c1.#d1.#g1)[P],#G-2[M],WXY,(#G-2.#G-1.#g.c1.#d1)[P],#g1[M],WXY,(#G-2.#G-1.#g)[P],(c1.#d1.#g1)[MP],WX,(#G-2.#G-1.#g)[P],(c1.#d1.#g1)[MP],WX,(#G-2.#G-1.#g.c1.#d1.#g1)[MOP],WY,#G-2[P],(#G-1.#g.c1.#d1)[P],#g1[M],WXY,(#G-2.#G-1.#g.c1.#d1.#g1)[MO],WX,#G-2[P],(#G-1.#g)[P],(c1.#d1.#g1)[M],WXY,(#D-1.#d.g.#a)[P],(#a.#d1.g1)[MP],W,(#D-1.#d.g.#a.#d1.g1)[MN],W,(#D-1.#d.g.#a.#d1.g1)[MP],WXY,(#D-1.#d.g.#a.#d1)[P],g1[M],WXY,#D-1[P],(#d.g.#a.#d1.g1)[MP],WXY,(#D-1.#d.g)[P],(#a.#d1)[P],g1[NOP],WXY,#D-1[P],(#d.g.#a)[P],(#d1.g1)[M],WXY,(#D-1.#d)[P],(g.#a.#d1.g1)[MP],W,(d1.f1)[O],(#A-2.#A-1.f.#a)[MO],W,f1[O],(#A-2.#A-1.f)[P],(#a.d1)[NO],VX,(#A-2.#A-1.f)[P],(#a.d1.f1)[M],WY,(d1.f1)[O],(#A-2.#A-1.f)[P],#a[M],WY,(d1.f1)[O],(#A-2.#A-1.f.#a)[MO],WX,#A-2[P],(#A-1.f.#a.d1.f1)[MP],W,(d1.f1)[OP],(#A-2.#A-1.f)[P],#a[M],WXY,(#A-2.#A-1)[P],(f.#a)[P],(d1.f1)[NP],V,(F-1.#g.c1.f1.#g1)[O],F-2[MP],WY,(F-1.#g.c1)[P],(f1.#g1)[M],WXY,(F-1.#g.c1)[P],(f1.#g1)[MP],WX,(F-2.F-1.#g)[P],(c1.f1.#g1)[MP],WX,F-1[P],(#g.c1.f1.#g1)[MO],WX,(F-1.#g.c1)[P],(f1.#g1)[M],WY,#g1[O],(F-2.F-1.#g.c1)[P],f1[M],WY,(f1.#g1)[O],(F-2.F-1.#g.c1)[MO],W,(c1.#d1)[P],#g1[P],#G-2[P],(#G-1.#g)[NOP],V,#G-2[P],(#G-1.#g.c1.#d1.#g1)[MP],WY,(c1.#d1.#g1)[O],(#G-2.#G-1.#g)[MO],W,(#g.c1.#d1.#g1)[O],(#G-2.#G-1)[NOP],WXY,(#g.c1.#d1.#g1)[O],(#G-2.#G-1)[NOP],VY,#G-2[P];"],"id":1,"instruments":["piano","piano"],"alternatives":["",""]},{"bpm":120,"baseBeats":0.25,"scores":["V,5<V>,VX,UW,UY,V,5<V>,U,VX,V,VWX,UY,V,5<V>,UY,VX,UWX,V,5<V>,UY,V,5<V>,V,5<V>,VX,UWX,VX,UV,U,T,VWXY,U,U,V,5<V>,U,UY,UVY,V,T,U,VY,V,U,VWX,VW,UWY,UVY,V,U,V,5<V>,V,5<V>,V,5<V>,TY,U,U,UY,VWXY,V,5<V>,VX,V,V,TV,U,U,UY,VWX,UY,T,U,VX,V,VWXY,V,5<V>,V,5<V>,V,5<V>,VX,UWXY,U,U,UY,V,5<V>,VX,V,VWXY,UVY,UWX,VWXY,UY,V,5<V>,V,5<V>,UY,UVY,UV,U,U,VWXY,U,V,5<V>,VY,UV,U,V,5<V>,UY,V,5<V>,U,VX,TV,U,U,V,5<V>,VX,V,VWXY,VY,V,V,V,UVWX,TY,U,UY,VWXY,UY,U,VY,UV,U,VX,V,VWXY,VX,V,VW,U,VX,V,UVY,V,VWXY,UY,U,TY;","(#G-1.#g.c1.#d1.#g1)[MP],WY,(#g.c1.#d1.#g1)[O],(#G-2.#G-1)[MO],W,(#G-1.#g.c1.#d1)[P],#g1[P],#G-2[NOP],WXY,(#D-1.#d.g.#a.#d1.g1)[MN],W,#D-1[P],(#D-1.#d.g.#a.#d1.g1)[MNOP],#D-1[P],(#d.g.#a.#d1.g1)[MO],WX,(#D-1.#d.g.#a.#d1.g1)[MO],WX,(#D-1.#d.g.#a)[P],(#d1.g1)[MP],WX,(#D-1.#d.g)[O],(#a.#d1.g1)[M],WXY,(#D-1.#d)[P],(g.#a.#d1.g1)[MP],WX,#D-1[P],(#d.g.#a.#d1.g1)[MP],WX,#A-2[P],(#A-1.f.#a.d1.f1)[MO],WX,(#A-2.#A-1.f)[P],(#a.d1.f1)[M],WXY,(#A-2.#A-1)[P],(f.#a.d1.f1)[MP],WX,#A-2[P],(#A-1.f.#a)[P],(d1.f1)[M],WXY,(#A-2.#A-1)[MP],WXY,(#A-2.#A-1.c2.c3)[MNO],#A-1[P],(#d2.#d3)[P],#A-2[MO],WX,(#A-2.#A-1)[M],WX,(F-1.f2)[P],(#g2.f3)[P],F-2[MO],UV,(f2.#g2.f3)[L],(f.c1.f2.#g2.f3)[LMO],WX,f[MNOP],c1[MOP],WY,(f2.f3)[L],#G-1[MP],WXY,(#d.#d2.#d3)[L],#g[P],#g[MP],WXY,(c1.#d2.#d3)[LMP],V,(c2.c3)[LMP],WXY,(#g.#d2.#d3)[L],#d[MP],V,(#a.c2.c3)[L],#d1[MP],WY,g1[MN],UWY,#a1[LMP],WXY,(f1.#a1)[P],d2[L],#A-1[MP],WXY,f[MP],WXY,#a[MP],WXY,(d1.f1.#a1)[LMO],WXY,f[L],(#a.c2.c3)[L],(#d2.#d3)[MO],WX,F-1[P],(f2.#g2.f3)[MNOP],f[P],(f2.#g2.f3)[MP],WX,#g[MO],WXY,(c1.f2.#g2)[P],f3[M],TV,#g[L],(f2.f3)[L],#G-1[MO],WXY,(#d.#d2.#d3)[MNO],#g[MOP],WY,c1[P],(#d2.#d3)[LMP],WXY,(f2.f3)[L],#g[MO],WX,#d2[P],#d3[MP],WXY,#d[MP],WXY,#a[MP],WXY,#d1[MP],WXY,g1[MO],UWXY,#a1[L],#a[MO],WX,(#a1.d2)[LP],#A-1[MP],WXY,f[MO],WXY,#a[MP],WXY,(d1.f1)[LMP],UWY,(f.c2)[P],c3[MNOP],#a[P],(#d2.#d3)[MP],WXY,(F-1.f2.#g2)[P],f3[M],WXY,f[P],(f2.#g2.f3)[MP],WX,#g[MO],WX,(c1.f2)[P],(#g2.f3)[LMP],UV,#g[L],(f2.f3)[L],#G-1[MO],WY,(#d.#d2.#d3)[L],#g[MP],WXY,(c1.#d2)[P],#d3[M],UV,(c2.c3)[L],#g[MP],WXY,#d2[P],#d3[MP],WXY,#d[MP],WXY,(#a.#a1.#a2)[L],#d1[P],(c2.c3)[MP],TV,g1[L],(#a.#a1)[L],(f1.#a1)[P],d2[M],WXY,#A-1[MO],WXY,f[MP],WXY,#a[MP],V,f[M],V,(c2.c3)[LMP],WY,(f.#a1.#a2)[LMO],WX,#C-1[P],(#a1.#a2)[L],#G-1[MP],WXY,#c[P],(#g1.#g2)[MNOP],#c[MO],WXY,(#g.#g1.#g2)[L],#c1[MP],UV,f1[L],#g1[MO],WXY,#c1[MP],WXY,#g[MO],WXY,#c1[MP],W,(c2.c3)[L],#g[MO],WXY,#c1[P],(#a1.#a2)[LMP],WXY,#A-1[P],(#a1.#a2)[MNOP],f[MO],WXY,(#a.#g1.#g2)[L],(#g1.#g2)[MP],UV;"],"id":2,"instruments":["piano","piano"],"alternatives":["",""]},{"bpm":120,"baseBeats":0.25,"scores":["U,V,5<V>,UX,UV,V,T,TX,VWY,UX,UX,VWX,U,VX,V,VWXY,UY,VY,UV,TY,VWY,U,VX,V,VWX,UY,UY,VY,UVY,VWX,UY,VWXY,UY,U,VY,V,V,5<V>,UY,UY,VWX,VW,UWY,VXY,UWXY,UVWX,VWX,UY,U,U,VX,UV,T,VWY,VW,UWY,V,5<V>,U,VXY,VWXY,UV,U,VX,UWX,UY,U,UXY,UWXY,VY,VWXY,VX,V,VWXY,V,5<V>,V,5<V>,VY,V,VY,UV,VWX,U,U,VY,V,VY,UV,T,V,5<V>,VWXY,VXY,VWXY,V,VWXY,UX,V,UV,U,UY,U,V,5<V>,U,U,VWX,UX,UY,VWXY,VXY,UW,U,UY,T,UY,VWX,U,UY,UVY,V,T,U,U,V,5<V>,U,U,VX,V,UVWXY,UY,T,U,UY,UY,TY,U,V,5<V>,UY,UY,U,V,5<V>,U,V,5<V>,UY,VY,V,V,5<V>,VWX,U,VX;","f[L],#a[MP],WXY,f1[MP],WXY,(#A-1.f)[P],(#a.f1)[P],(#g1.#c2)[LM],WXY,(#A-1.f.#a)[P],(f1.#g1.#c2)[LMP],W,#g1[P],c2[O],#g2[LP],(#A-1.#a)[NO],VXY,(g1.c2.g2)[MNP],C-1[MO],F-1[O],WY,(F-2.F-1.#g1)[P],(c2.#g2)[LO],VWX,(F-1.c)[L],f[MO],WXY,f1[P],#g1[P],f2[NOP],WXY,F-1[P],(F-1.c)[MP],WXY,f[MP],UV,(#G-2.#G-1.#g1.c2.#g2)[LMO],WX,#g1[P],(c2.#g2)[MNP],(#G-1.#d.#g)[MNO],X,(g1.c2.g2)[MO],WX,#G-1[P],#d[MP],WX,#g[MO],WXY,(f1.c2.f2)[LP],(#D-1.#A-1.#d.g1.#a1)[O],(#d2.g2)[NOP],UVY,(g1.#a1.#d2.g2)[MNO],(#D-2.#D-1)[MN],W,g1[P],(#a1.#d2.g2)[MNOP],#D-1[P],#A-1[MP],WXY,(#d.f1.#a1.f2)[L],(f1.#a1.f2)[MP],V,(#A-2.#A-1)[MP],WXY,f1[MO],WXY,(#a1.d2)[LP],#A-1[P],(f.#a)[M],WY,(f1.#a1.f2)[MN],WX,#A-1[P],f[NOP],WX,#a[P],(g1.g2)[MOP],UWY,(#g1.c2.#g2)[O],(F-2.F-1)[LM],WX,(F-1.c)[MNO],f[MN],W,f1[P],(#g1.f2)[L],(F-1.c)[MOP],WY,f[MO],UWXY,(#G-2.#G-1.#g1)[P],(c2.#g2)[LMP],WX,(#g1.c2)[P],#g2[MNP],(#G-1.#d.#g)[MN],W,(#g1.c2)[P],#g2[MP],WXY,(#G-1.#d)[MP],WXY,(#g.#a1.#d2.#a2)[L],(#a1.#d2.#a2)[MOP],WX,(#D-1.#d)[MP],UV,g[L],(#D-1.#d.#a.#d1)[P],g1[MP],UWX,(#D-1.#A-1)[LP],(#d.g.#a.#d1.g1)[L],#A-1[MP],WXY,(#A-2.#A-1)[O],f[P],(#a.d1.f1)[LNOP],V,(f.#a)[P],(d1.f1)[MNOP],(#A-2.#A-1)[MO],WX,#g1[P],(c2.#g2)[MP],WXY,#A-2[MP],WXY,(#A-1.g1.c2)[P],g2[M],WXY,F-1[MP],V,(F-2.F-1.#g1.c2)[P],#g2[M],UWXY,F-1[P],c[MNO],f[MOP],WY,(f1.#g1.f2)[L],F-1[P],c[M],V,f[MP],UV,(#G-2.#G-1.#g1.c2.#g2)[LMO],WX,(#g1.c2.#g2)[MNO],#g[O],(#G-1.#d)[MO],WY,(g1.c2.g2)[MOP],WXY,(#G-1.#d)[M],V,#g[MO],WY,(f1.c2.f2)[LO],(#D-1.#A-1.#d.g1.#a1)[P],(#d2.g2)[NOP],UV,(g1.#a1.#d2.g2)[L],(#D-2.#D-1)[MO],WXY,(g1.#a1.#d2.g2)[L],(#D-1.#A-1)[MP],WXY,(#d.f1.#a1.f2)[L],(f1.#a1.f2)[L],(#A-2.#A-1)[MO],W,f1[MN],WX,(#a1.d2)[LP],(#A-1.f.#a)[MNO],(f1.#a1)[P],f2[MOP],WX,(#A-1.f)[M],WX,(#a.g1.g2)[L],#C-1[MO],WXY,(#C-2.#C-1.#g1.#c2.#g2)[LMP],WXY,#C-1[LP],#c[MP],WY,(g1.#c2.g2)[L],#C-1[MP],WXY,(#c.f1)[P],(#c2.f2)[LMP],WXY,#C-1[P],(#c.#g1.#c2.#g2)[LMO],WX,#c[L],(#c1.g1)[L],g1[P],(#c2.g2)[MP],WX,#c[MO],WX,(#c1.f1.f2)[L],#d[MO],WXY,(#D-1.#d.g1.#a1)[P],(#d2.g2)[LM],WXY,g1[LP],(#d.#a.g1.#a1.#d2)[LMO],WX,(#d.g1)[L],(#a.#a1)[P],#d2[MP],WXY,#a[MP],WXY,#D-1[P],(#d.#g1.#g2)[LMO],WX,(g1.#a1)[P],g2[L],(#D-1.#d)[MP],WXY,(f1.#a1)[P],f2[MP],WXY,#D-1[MP],WXY,#d[P],(#d1.#d2)[L],(C-1.F-1)[MP],WXY,(F-2.F-1.#g.c1.f1.#g1)[L],(F-1.#g.c1)[P],(f1.#g1)[MP],WX,F-1[P],(F-1.#g.c1)[P],(f1.#g1)[M],WXY,(F-2.F-1)[P],(#g.c1.f1)[P],#g1[NOP],V,F-1[P],(#g.c1.f1.#g1)[MP],WX,(F-1.#g.c1.f1.#g1)[MO],W,(F-2.F-1.#g.c1.f1.#g1)[L],(F-1.#g)[P],(c1.f1.#g1)[MP];"],"id":3,"instruments":["piano","piano"],"alternatives":["",""]}],"audition":{"start":[0,0],"end":[2,258]}}