{"baseBpm":300,"musics":[{"bpm":300,"baseBeats":0.75,"scores":["mute[JK],mute[JK],mute[IL],mute[LM],mute[LM],mute[KL],mute[KL],mute[KL],mute[KL],mute[KL],mute[KL],mute[KL],mute[KL],mute[LM],mute[LM],mute[LM],mute[LM],mute[LM],mute[LM],mute[LM],mute[LM],mute[LM],mute[LM],mute[LM],mute[LM],mute[KL],mute[LM],mute[LM],mute[KL],5<UV>,mute[LM],mute[LM],mute[LM],mute[LM],mute[LM],mute[LM],mute[LM],mute[LM],mute[LM],mute[LM],mute[LM],mute[LM],mute[LM],mute[LM],mute[LM],mute[LM],mute[LM],mute[LM],mute[LM],mute[LM],mute[LM],mute[LM],mute[LM],mute[LM],mute[LM],mute[LM],mute[LM],mute[LM],mute[LM],mute[LM],mute[LM],mute[LM],mute[LM],mute[LM],mute[LM],mute[LM],mute[LM],mute[LM],mute[LM],mute[LM],mute[LM],mute[LM],mute[LM],mute[LM],mute[LM],mute[LM],mute[LM],mute[LM],mute[LM],mute[LM],mute[LM],mute[LM],mute[LM],mute[LM],mute[LM],mute[LM],mute[LM],mute[LM],mute[LM],mute[LM],mute[LM],mute[LM],mute[LM],mute[LM],mute[LM],mute[LM],mute[LM],mute[LM],mute[LM],mute[LM],mute[LM],mute[LM],mute[LM],mute[LM],mute[LM],mute[LM],mute[LM],mute[LM],mute[LM],mute[LM],mute[LM],mute[LM],mute[LM],mute[LM],mute[LM],mute[LM],mute[LM],mute[LM],mute[LM],mute[KL],mute[LM],mute[LM],mute[KL],mute[LM],mute[LM],mute[LM],mute[LM],mute[LM],mute[LM],mute[LM],mute[LM],mute[LM],mute[LM],mute[LM],mute[LM],mute[LM],mute[LM],mute[LM],mute[LM],mute[LM],mute[LM],mute[LM],mute[LM],mute[LM],mute[LM],mute[LM],mute[LM],mute[LM],mute[LM],mute[LM],mute[LM],mute[LM],mute[LM],mute[LM],mute[LM],mute[LM],mute[LM],mute[LM],mute[LM],mute[LM],mute[LM],mute[LM],mute[LM],mute[LM],mute[LM],mute[LM],mute[LM],mute[LM],mute[LM],mute[LM],mute[LM],mute[LM],mute[LM],mute[LM],mute[LM],mute[LM],mute[LM],mute[LM],mute[LM],mute[LM],mute[LM],mute[LM],mute[LM],mute[LM],mute[LM],mute[LM],mute[LM],mute[LM],mute[LM],mute[LM],mute[LM],mute[LM],mute[LM],mute[LM],mute[LM],mute[LM],mute[LM],mute[LM],mute[LM],mute[LM],mute[LM],mute[LM],mute[LM],mute[LM],mute[LM],mute[LM],mute[LM],mute[LM],mute[LM],mute[LM],mute[LM],mute[LM],mute[LM],mute[LM],mute[LM],mute[LM],mute[LM],mute[LM],mute[LM],mute[LM],mute[LM],mute[LM],mute[LM],mute[LM],mute[LM],mute[LM],mute[LM],mute[LM],mute[LM],mute[LM],mute[LM],mute[LM],mute[LM],mute[LM],mute[LM],mute[LM],mute[LM],mute[LM],mute[LM],mute[LM],mute[LM],mute[LM],mute[LM],mute[LM],mute[LM],mute[LM],mute[LM],mute[LM],mute[LM],mute[LM],mute[LM],mute[LM],mute[LM],mute[LM],mute[LM],mute[LM],mute[LMN],mute[JKM],5<UV>,5<UV>,5<UV>,5<UV>,mute[LM],mute[LM],mute[LM],mute[KMN],mute[KLN],mute[KLN],mute[KLN],mute[KLN],mute[KL],mute[KL],mute[LM],mute[LM],mute[LM],mute[LM],mute[LM],mute[LM],mute[LM],mute[K],mute[KLN],mute[LM],mute[LMN],mute[KL],mute[LM],mute[LM],mute[KLN],mute[KLN],mute[KL],mute[KL],mute[KLN],mute[KLN],mute[KL],mute[LM],mute[LM],mute[KLN],mute[LM],mute[LM],mute[LM],mute[LM],mute[LM],mute[LM],mute[LM],mute[LM],mute[LM],mute[KN],5<UV>,mute[LM],mute[KL],5<UV>,mute[LM],mute[LM],mute[LM],mute[LM],mute[LM],mute[LM],mute[K],mute[JKM],mute[JK],mute[JKM],mute[KL],mute[LM],mute[LM],mute[KLN],mute[LM],mute[LMN],mute[KL],mute[KL],mute[KLN],mute[KLN],mute[KL],mute[LM],mute[LM],mute[KLN],mute[LM],mute[LMN];","f1[JK],a1[JK],c2[IL],#a1[LM],a1[LM],#a1[KL],c2[KL],d2[KL],e2[KL],f2[KL],c2[KL],f2[KL],a2[KL],(g2.c)[LM],f2[LM],e2[LM],d2[LM],(c2.e)[LM],#a1[LM],a1[LM],g1[LM],(a1.f)[LM],c2[LM],f1[LM],a1[LM],d2[KL],f[LM],e[LM],f[KL],(c2.g)[M],d2[M],c2[M],b1[LM],(c2.a)[LM],e2[LM],(d2.b)[LM],f2[LM],(e2.c1)[LM],d2[LM],(c2.g)[LM],b1[LM],(a1.c1)[LM],c2[LM],(g1.e1)[LM],c2[LM],(f1.d1)[LM],(e2.c1)[LM],(d2.b)[LM],(c2.a)[LM],(b1.g)[LM],(d2.f)[LM],(g1.e)[LM],(b1.d)[LM],(c2.e)[LM],g[LM],c[LM],e[LM],a[LM],e2[LM],a1[LM],c2[LM],f1[LM],c1[LM],f[LM],a[LM],d[LM],a1[LM],d1[LM],f1[LM],#a1[LM],f[LM],#A-1[LM],d[LM],g[LM],d2[LM],g1[LM],#a1[LM],e1[LM],#a[LM],e[LM],g[LM],c[LM],g1[LM],c1[LM],e1[LM],a1[LM],(c2.e)[LM],(f1.A-1)[LM],(a1.c)[LM],(d1.f)[LM],(f1.a)[LM],(#a.d)[LM],(d1.f)[LM],(g1.#A-1)[LM],(#a1.d)[LM],(e1.G-1)[LM],(g1.#A-1)[LM],(c1.e)[LM],(e1.g)[LM],(a.c)[LM],(c1.e)[LM],(f1.A-1)[LM],(a1.c)[LM],(d1.F-1)[LM],(f1.A-1)[LM],(#a1.d)[LM],(d2.f)[LM],(g1.#A-1)[LM],(#a1.d)[LM],(c1.e)[LM],g[LM],c[LM],e[LM],(e1.g)[LM],#a[LM],e[LM],g[LM],(f1.a)[LM],c1[LM],f[LM],a[LM],d1[KL],f1[LM],e1[LM],f1[KL],(g1.c1)[LM],#a[LM],(a1.c1)[LM],#d1[LM],(#a1.d1)[LM],f1[LM],(c2.#d1)[LM],d1[LM],(f1.#d1)[LM],c1[LM],(#a1.d1)[LM],f1[LM],(d2.#a)[LM],d1[LM],(c2.#d)[LM],(#a1.d1)[LM],(a1.c1)[LM],(g1.#a)[LM],(f1.a)[LM],(#d1.c1)[LM],(d1.f)[LM],(c1.a)[LM],(d1.#A-1)[LM],#a[LM],f1[LM],d1[LM],#a1[LM],G-1[LM],d[LM],#A-1[LM],g[LM],d2[LM],g1[LM],#a1[LM],e1[LM],#a[LM],e[LM],g[LM],c[LM],c1[LM],g1[LM],e1[LM],c2[LM],A-1[LM],e[LM],c[LM],a[LM],e2[LM],a1[LM],c2[LM],f1[LM],c1[LM],f[LM],a[LM],d[LM],d1[LM],a1[LM],f1[LM],d2[LM],(a1.f)[LM],(f2.d)[LM],(d2.f)[LM],(#a1.g)[LM],(g1.#a)[LM],(d2.d)[LM],(#a1.g)[LM],(g2.#A-1)[LM],(d2.d)[LM],(#a2.G-1)[LM],(g2.#A-1)[LM],(e2.c)[LM],(c2.e)[LM],(g2.G-1)[LM],(e2.c)[LM],(#a2.E-1)[LM],(g2.G-1)[LM],(e2.C-1)[LM],(c3.E-1)[LM],(a2.F-1)[LM],c3[LM],f2[LM],a2[LM],(c2.A-1)[LM],f2[LM],#d2[LM],d2[LM],(#d2.c)[LM],g2[LM],c2[LM],#d2[LM],a1[LM],#d2[LM],(d2.#A-1)[LM],(c2.A-1)[LM],(d2.#A-1)[LM],#a1[LM],(e2.c)[LM],#a1[LM],(f2.d)[LM],#a1[LM],(g2.e)[LM],#a1[LM],(a1.f)[LM],g2[LM],(f2.c)[LM],e2[LM],(d2.f)[LM],f2[LM],(c2.a)[LM],f2[LM],(#a1.g)[LM],(a2.f)[LM],(g2.e)[LM],(f2.d)[LM],(e2.c)[LM],(g2.#A-1)[LM],(c2.A-1)[LM],(e2.G-1)[LM],(f2.A-1)[LM],(c2.c)[LM],(a2.F-1)[LM],(f2.A-1)[LM],(c2.c)[LM],(a1.f)[LM],(f2.A-1)[LM],(c2.c)[LM],(a1.f)[LM],(f1.a)[LM],(c2.c)[LM],(a1.f)[LM],(f1.a)[LM],c1[LM],(a1.f)[LMN],(f1.a)[LM],c1[JKM],(#a2.c)[MN],a2[L],g2[M],a2[M],g2[M],a2[L],g2[L],f2[MN],g2[MN],(f2.f)[LMN],c[LM],A-1[LMN],c[LM],F-1[KLN],a1[KLN],#a1[KLN],(#c2.e)[KLN],(d2.f)[KL],#g[KL],a[LMN],#c2[LM],d2[LM],e2[LMN],f2[LM],#g[LM],a[LM],b[LM],c1[KLN],#d2[LM],d2[LMN],#d2[KL],(#f1.#a)[LM],a[LM],(g1.#a)[KLN],#c[KLN],d[KL],f1[KL],#g1[KLN],(a1.c)[KLN],#d[KL],(g1.e)[LM],#f1[LM],g1[KLN],(e2.d)[LM],(g1.#c)[LMN],(f1.d)[LM],e1[LM],(d1.b)[LM],(f1.d)[LM],(e1.c)[LMN],B-1[LM],(a1.A-1)[LM],c[LMN],(d2.B-1)[M],e2[M],d2[M],#c2[LM],(d2.e)[KL],a[M],b[M],a[MN],#g[LM],(#c2.a)[LM],b1[LMN],a1[LM],g1[LM],f1[LM],e1[LM],d1[JKM],(f1.A-1)[JK],(a1.#c)[JKM],e[KL],g1[LM],f1[LM],g1[KLN],(a1.d)[LM],#c[LMN],(b1.d)[KL],(#c2.e)[KL],(d2.f)[KLN],g[KLN],a[KL],#c2[LM],b1[LM],#c2[KLN],(d2.g)[LM],f[LMN];"],"id":1,"instruments":["piano","piano"],"alternatives":["",""]},{"bpm":300,"baseBeats":0.75,"scores":["mute[JK],mute[JK],mute[IL],mute[LM],mute[LM],mute[KL],mute[KL],mute[KL],mute[KL],mute[KL],mute[KL],mute[KL],mute[KL],mute[LM],mute[LM],mute[LM],mute[LM],mute[LM],mute[LM],mute[LM],mute[LM],mute[LM],mute[LM],mute[LM],mute[LM],mute[KL],mute[LM],mute[LM],mute[KL],5<UV>,mute[LM],mute[LM],mute[LM],mute[LM],mute[LM],mute[LM],mute[LM],mute[LM],mute[LM],mute[LM],mute[LM],mute[LM],mute[LM],mute[LM],mute[LM],mute[LM],mute[LM],mute[LM],mute[LM],mute[LM],mute[LM],mute[LM],mute[LM],mute[LM],mute[LM],mute[LM],mute[LM],mute[LM],mute[LM],mute[LM],mute[LM],mute[LM],mute[LM],mute[LM],mute[LM],mute[LM],mute[LM],mute[LM],mute[LM],mute[LM],mute[LM],mute[LM],mute[LM],mute[LM],mute[LM],mute[LM],mute[LM],mute[LM],mute[LM],mute[LM],mute[LM],mute[LM],mute[LM],mute[LM],mute[LM],mute[LM],mute[LM],mute[LM],mute[LM],mute[LM],mute[LM],mute[LM],mute[LM],mute[LM],mute[LM],mute[LM],mute[LM],mute[LM],mute[LM],mute[LM],mute[LM],mute[LM],mute[LM],mute[LM],mute[LM],mute[LM],mute[LM],mute[LM],mute[LM],mute[LM],mute[LM],mute[LM],mute[LM],mute[LM],mute[LM],mute[LM],mute[LM],mute[LM],mute[LM],mute[KL],mute[LM],mute[LM],mute[KL],mute[LM],mute[LM],mute[LM],mute[LM],mute[LM],mute[LM],mute[LM],mute[LM],mute[LM],mute[LM],mute[LM],mute[LM],mute[LM],mute[LM],mute[LM],mute[LM],mute[LM],mute[LM],mute[LM],mute[LM],mute[LM],mute[LM],mute[LM],mute[LM],mute[LM],mute[LM],mute[LM],mute[LM],mute[LM],mute[LM],mute[LM],mute[LM],mute[LM],mute[LM],mute[LM],mute[LM],mute[LM],mute[LM],mute[LM],mute[LM],mute[LM],mute[LM],mute[LM],mute[LM],mute[LM],mute[LM],mute[LM],mute[LM],mute[LM],mute[LM],mute[LM],mute[LM],mute[LM],mute[LM],mute[LM],mute[LM],mute[LM],mute[LM],mute[LM],mute[LM],mute[LM],mute[LM],mute[LM],mute[LM],mute[LM],mute[LM],mute[LM],mute[LM],mute[LM],mute[LM],mute[LM],mute[LM],mute[LM],mute[LM],mute[LM],mute[LM],mute[LM],mute[LM],mute[LM],mute[LM],mute[LM],mute[LM],mute[LM],mute[LM],mute[LM],mute[LM],mute[LM],mute[LM],mute[LM],mute[LM],mute[LM],mute[LM],mute[LM],mute[LM],mute[LM],mute[LM],mute[LM],mute[LM],mute[LM],mute[LM],mute[LM],mute[LM],mute[LM],mute[LM],mute[LM],mute[LM],mute[LM],mute[LM],mute[LM],mute[LM],mute[LM],mute[LM],mute[LM],mute[LM],mute[LM],mute[LM],mute[LM],mute[LM],mute[LM],mute[LM],mute[LM],mute[LM],mute[LM],mute[LM],mute[LM],mute[LM],mute[LM],mute[LM],mute[LM],mute[LM],mute[LM],mute[LM],mute[LM],mute[LMN],mute[JKM],5<UV>,5<UV>,5<UV>,5<UV>,mute[LM],mute[LM],mute[LM],mute[KMN],mute[KLN],mute[KLN],mute[KLN],mute[KLN],mute[KL],mute[KL],mute[LM],mute[LM],mute[LM],mute[LM],mute[LM],mute[LM],mute[LM],mute[K],mute[KLN],mute[LM],mute[LMN],mute[KL],mute[LM],mute[LM],mute[KLN],mute[KLN],mute[KL],mute[KL],mute[KLN],mute[KLN],mute[KL],mute[LM],mute[LM],mute[KLN],mute[LM],mute[LM],mute[LM],mute[LM],mute[LM],mute[LM],mute[LM],mute[LM],mute[LM],mute[KN],5<UV>,mute[LM],mute[KL],5<UV>,mute[LM],mute[LM],mute[LM],mute[LM],mute[LM],mute[LM],mute[K],mute[JKM],mute[JK],mute[JKM],mute[KL],mute[LM],mute[LM],mute[KLN],mute[LM],mute[LMN],mute[KL],mute[KL],mute[KLN],mute[KLN],mute[KL],mute[LM],mute[LM],mute[KLN],mute[LM],mute[LMN],mute[KL],mute[KL],mute[LM],mute[LM],mute[LM],mute[K],mute[KL],mute[KL],5<UV>,mute[LM],mute[LM],mute[K],5<UV>,5<UV>,5<UV>,5<UV>,mute[KLN],mute[KLN],mute[KL],mute[KL],mute[LM],mute[LM],mute[LM],mute[LM],mute[LM],mute[LM],mute[LM],mute[K],mute[KLN],mute[LM],mute[LMN],mute[KL],mute[LM],mute[LM],mute[KLN],mute[KLN],mute[KL],mute[KL],mute[KLN],mute[KLN],mute[KL],mute[LM],mute[LM],mute[KLN],mute[LM],mute[LM],mute[LM],mute[LM],mute[LM],mute[LM],mute[LM],mute[LM],mute[LM],mute[KN],5<UV>,mute[LM],mute[KL],5<UV>,mute[LM],mute[LM],mute[LM],mute[LM],mute[LM],mute[LM],mute[K],mute[JKM],mute[JK],mute[JKM],mute[KL],mute[LM],mute[LM],mute[KLN],mute[LM],mute[LMN],mute[KL],mute[KL],mute[KLN],mute[KLN],mute[KL],mute[LM],mute[LM],mute[KLN],mute[LM],mute[LMN],mute[KL],mute[KL],mute[LM],mute[LM],mute[LM],mute[K],mute[KL],mute[KL],mute[KLN],mute[LM],mute[LM],mute[LM],mute[LM],mute[LM],mute[LM],mute[LM],mute[LM],mute[LM],mute[LM],mute[LM],mute[LM],mute[LM],mute[LM],mute[LM],mute[LM],mute[LM],mute[KMN],mute[KL],mute[KL],mute[KLN],mute[KLN],mute[KL],mute[LM],mute[LM],mute[KLN],mute[KLN],mute[KL],mute[KL],mute[LM],mute[LM],mute[LM],mute[LM],mute[LM],mute[LM],mute[LM],mute[LM],mute[LM],mute[LM],mute[LM],mute[LM],mute[LM],mute[LM],mute[LM],mute[LM],mute[LM],mute[LM],mute[LM],mute[LM],mute[LM],mute[KL],mute[KL],mute[KLN],mute[KLN],mute[KL],mute[LM],mute[LM],mute[KLN],mute[KLN],mute[KL],mute[KL],mute[LM],mute[LM],mute[LM],mute[LM],mute[LM],mute[LM],mute[LM],mute[LM],mute[LM],mute[LM],mute[LM],mute[LM],mute[LM],mute[LM],mute[LM],mute[LM],mute[LM],mute[LM],mute[LM],mute[LM],mute[LM],mute[LM],mute[LM],mute[LM],mute[LM],mute[LM],mute[LM],mute[LM],mute[LM],mute[LM],mute[LM],mute[LM],mute[LM],mute[LM],mute[LM],mute[LM],mute[LM],mute[LM],mute[LM],mute[LM],mute[KM],mute[KLN],mute[KLN],mute[KL],mute[KL],mute[LM],mute[LM],mute[LM],mute[LM],mute[LM],mute[LM],mute[LM],mute[K],mute[KLN],mute[LM],mute[LMN],mute[KL],mute[LM],mute[LM],mute[KLN],mute[KLN],mute[KL],mute[KL],mute[KLN],mute[KLN],mute[KL],mute[LM],mute[LM],mute[KLN],mute[LM],mute[LM],mute[LM],mute[LM],mute[LM],mute[LM],mute[LM],mute[LM],mute[LM],mute[KN],5<UV>,mute[LM],mute[KL],5<UV>,mute[LM],mute[LM],mute[LM],mute[LM],mute[LM],mute[LM],mute[K],mute[JKM],mute[JK],mute[JKM],mute[KL],mute[LM],mute[LM],mute[KLN],mute[LM],mute[LMN],mute[KL],mute[KL],mute[KLN],mute[KLN],mute[KL],mute[LM],mute[LM],mute[KLN],mute[LM],mute[LMN],mute[KL],mute[KL],mute[LM],mute[LM],mute[LM],mute[K],mute[KL],mute[KL],mute[KLN],mute[LM],mute[LM],mute[LM],mute[LM],mute[LM],mute[LMN],mute[KLN],mute[KLN],mute[KL],mute[KL],mute[LM],mute[LM],mute[LM],mute[LM],mute[LM],mute[LM],mute[LM],mute[K],mute[KLN],mute[LM],mute[LMN],mute[KL],mute[LM],mute[LM],mute[KLN],mute[KLN],mute[KL],mute[KL],mute[KLN],mute[KLN],mute[KL],mute[LM],mute[LM],mute[KLN],mute[LM],mute[LM],mute[LM],mute[LM],mute[LM],mute[LM],mute[K];","f1[JK],a1[JK],c2[IL],#a1[LM],a1[LM],#a1[KL],c2[KL],d2[KL],e2[KL],f2[KL],c2[KL],f2[KL],a2[KL],(g2.c)[LM],f2[LM],e2[LM],d2[LM],(c2.e)[LM],#a1[LM],a1[LM],g1[LM],(a1.f)[LM],c2[LM],f1[LM],a1[LM],d2[KL],f[LM],e[LM],f[KL],(c2.g)[M],d2[M],c2[M],b1[LM],(c2.a)[LM],e2[LM],(d2.b)[LM],f2[LM],(e2.c1)[LM],d2[LM],(c2.g)[LM],b1[LM],(a1.c1)[LM],c2[LM],(g1.e1)[LM],c2[LM],(f1.d1)[LM],(e2.c1)[LM],(d2.b)[LM],(c2.a)[LM],(b1.g)[LM],(d2.f)[LM],(g1.e)[LM],(b1.d)[LM],(c2.e)[LM],g[LM],c[LM],e[LM],a[LM],e2[LM],a1[LM],c2[LM],f1[LM],c1[LM],f[LM],a[LM],d[LM],a1[LM],d1[LM],f1[LM],#a1[LM],f[LM],#A-1[LM],d[LM],g[LM],d2[LM],g1[LM],#a1[LM],e1[LM],#a[LM],e[LM],g[LM],c[LM],g1[LM],c1[LM],e1[LM],a1[LM],(c2.e)[LM],(f1.A-1)[LM],(a1.c)[LM],(d1.f)[LM],(f1.a)[LM],(#a.d)[LM],(d1.f)[LM],(g1.#A-1)[LM],(#a1.d)[LM],(e1.G-1)[LM],(g1.#A-1)[LM],(c1.e)[LM],(e1.g)[LM],(a.c)[LM],(c1.e)[LM],(f1.A-1)[LM],(a1.c)[LM],(d1.F-1)[LM],(f1.A-1)[LM],(#a1.d)[LM],(d2.f)[LM],(g1.#A-1)[LM],(#a1.d)[LM],(c1.e)[LM],g[LM],c[LM],e[LM],(e1.g)[LM],#a[LM],e[LM],g[LM],(f1.a)[LM],c1[LM],f[LM],a[LM],d1[KL],f1[LM],e1[LM],f1[KL],(g1.c1)[LM],#a[LM],(a1.c1)[LM],#d1[LM],(#a1.d1)[LM],f1[LM],(c2.#d1)[LM],d1[LM],(f1.#d1)[LM],c1[LM],(#a1.d1)[LM],f1[LM],(d2.#a)[LM],d1[LM],(c2.#d)[LM],(#a1.d1)[LM],(a1.c1)[LM],(g1.#a)[LM],(f1.a)[LM],(#d1.c1)[LM],(d1.f)[LM],(c1.a)[LM],(d1.#A-1)[LM],#a[LM],f1[LM],d1[LM],#a1[LM],G-1[LM],d[LM],#A-1[LM],g[LM],d2[LM],g1[LM],#a1[LM],e1[LM],#a[LM],e[LM],g[LM],c[LM],c1[LM],g1[LM],e1[LM],c2[LM],A-1[LM],e[LM],c[LM],a[LM],e2[LM],a1[LM],c2[LM],f1[LM],c1[LM],f[LM],a[LM],d[LM],d1[LM],a1[LM],f1[LM],d2[LM],(a1.f)[LM],(f2.d)[LM],(d2.f)[LM],(#a1.g)[LM],(g1.#a)[LM],(d2.d)[LM],(#a1.g)[LM],(g2.#A-1)[LM],(d2.d)[LM],(#a2.G-1)[LM],(g2.#A-1)[LM],(e2.c)[LM],(c2.e)[LM],(g2.G-1)[LM],(e2.c)[LM],(#a2.E-1)[LM],(g2.G-1)[LM],(e2.C-1)[LM],(c3.E-1)[LM],(a2.F-1)[LM],c3[LM],f2[LM],a2[LM],(c2.A-1)[LM],f2[LM],#d2[LM],d2[LM],(#d2.c)[LM],g2[LM],c2[LM],#d2[LM],a1[LM],#d2[LM],(d2.#A-1)[LM],(c2.A-1)[LM],(d2.#A-1)[LM],#a1[LM],(e2.c)[LM],#a1[LM],(f2.d)[LM],#a1[LM],(g2.e)[LM],#a1[LM],(a1.f)[LM],g2[LM],(f2.c)[LM],e2[LM],(d2.f)[LM],f2[LM],(c2.a)[LM],f2[LM],(#a1.g)[LM],(a2.f)[LM],(g2.e)[LM],(f2.d)[LM],(e2.c)[LM],(g2.#A-1)[LM],(c2.A-1)[LM],(e2.G-1)[LM],(f2.A-1)[LM],(c2.c)[LM],(a2.F-1)[LM],(f2.A-1)[LM],(c2.c)[LM],(a1.f)[LM],(f2.A-1)[LM],(c2.c)[LM],(a1.f)[LM],(f1.a)[LM],(c2.c)[LM],(a1.f)[LM],(f1.a)[LM],c1[LM],(a1.f)[LMN],(f1.a)[LM],c1[JKM],(#a2.c)[MN],a2[L],g2[M],a2[M],g2[M],a2[L],g2[L],f2[MN],g2[MN],(f2.f)[LMN],c[LM],A-1[LMN],c[LM],F-1[KLN],a1[KLN],#a1[KLN],(#c2.e)[KLN],(d2.f)[KL],#g[KL],a[LMN],#c2[LM],d2[LM],e2[LMN],f2[LM],#g[LM],a[LM],b[LM],c1[KLN],#d2[LM],d2[LMN],#d2[KL],(#f1.#a)[LM],a[LM],(g1.#a)[KLN],#c[KLN],d[KL],f1[KL],#g1[KLN],(a1.c)[KLN],#d[KL],(g1.e)[LM],#f1[LM],g1[KLN],(e2.d)[LM],(g1.#c)[LMN],(f1.d)[LM],e1[LM],(d1.b)[LM],(f1.d)[LM],(e1.c)[LMN],B-1[LM],(a1.A-1)[LM],c[LMN],(d2.B-1)[M],e2[M],d2[M],#c2[LM],(d2.e)[KL],a[M],b[M],a[MN],#g[LM],(#c2.a)[LM],b1[LMN],a1[LM],g1[LM],f1[LM],e1[LM],d1[JKM],(f1.A-1)[JK],(a1.#c)[JKM],e[KL],g1[LM],f1[LM],g1[KLN],(a1.d)[LM],#c[LMN],(b1.d)[KL],(#c2.e)[KL],(d2.f)[KLN],g[KLN],a[KL],#c2[LM],b1[LM],#c2[KLN],(d2.g)[LM],f[LMN],(e2.g)[KL],(f2.a)[KL],(a2.b)[LMN],g2[LM],(f2.#c1)[LM],e2[LMN],(f2.d1)[KL],(d2.b)[KL],(e2.a)[L],d2[MN],(e2.g)[LM],f[LM],g[LMN],(e2.a)[M],d2[L],#c2[M],d2[M],#c2[M],(d2.e)[MN],#c2[MN],b1[MN],#c2[MN],(d2.f)[KLN],(b1.#g)[KLN],(c2.a)[KL],#d2[KL],e2[LMN],#g[LM],a[LM],b[LMN],c1[LM],#d2[LM],e2[LM],#f2[LM],g2[KLN],#a[LM],a[LMN],#a[KL],(f2.#c)[LM],e2[LM],(f2.d)[KLN],#g1[KLN],a1[KL],c[KL],#d[KLN],(g1.e)[KLN],#a1[KL],(b1.d)[LM],#c[LM],d[KLN],(a1.b)[LM],(#g1.d)[LMN],(a1.c)[LM],B-1[LM],(#f2.A-1)[LM],(a1.c)[LM],(g1.B-1)[LMN],#f1[LM],(e1.e)[LM],g1[LMN],(#f1.a)[M],#a[M],a[M],#g[LM],(#d2.a)[KL],e2[M],#f2[M],e2[MN],#d2[LM],(e2.#g)[LM],#f[LMN],e[LM],d[LM],c[LM],B-1[LM],A-1[JKM],(e1.c)[JK],(#g1.e)[JKM],b1[KL],d[LM],c[LM],d[KLN],(a1.e)[LM],#g1[LMN],(a1.#f)[KL],(b1.#g)[KL],(c2.a)[KLN],d2[KLN],e2[KL],#g[LM],#f[LM],#g[KLN],(d2.a)[LM],c2[LMN],(d2.b)[KL],(e2.c1)[KL],(#f2.e1)[LMN],d1[LM],(#g2.c1)[LM],b[LMN],(a2.c1)[KL],f1[KL],d1[KLN],(#g2.b)[LM],#f2[LMN],(e2.e1)[LM],d2[LM],(c2.e)[LM],b1[LM],(a1.a)[LMN],c1[LM],e[LM],a[LMN],c[LM],(e1.e)[LM],(c2.A-1)[LM],(a1.c)[LM],(f2.F-1)[LMN],c2[LM],a2[LM],f2[LMN],(c3.A-1)[KL],f2[KL],(e2.c)[KLN],#d2[KLN],d2[KL],(#c2.#A-1)[LM],A-1[LM],#A-1[KLN],(c2.c)[KLN],(b1.d)[KL],(#a1.e)[KL],(a1.f)[LMN],g1[LM],(f1.c)[LM],g1[LMN],(a1.f)[LM],#a1[LM],(c2.a)[LM],d2[LM],(e2.g)[LMN],(d2.f)[LM],(c2.e)[LM],(d2.d)[LMN],(e2.c)[LM],(f2.#A-1)[LM],(g2.A-1)[LM],G-1[LM],(c2.A-1)[LMN],c[LM],F-1[LM],A-1[LMN],(#g1.C-1)[KL],c[KL],(f1.#c)[KLN],d[KLN],#d[KL],(g1.e)[LM],#g1[LM],g1[KLN],(f1.f)[KLN],(#d1.#f)[KL],(#c1.g)[KL],(c1.#g)[LMN],#a[LM],(f1.c1)[LM],#a[LMN],(c1.#g)[LM],g[LM],(#g.f)[LM],#d[LM],(#a.#c)[LMN],(c1.#d)[LM],(#c1.f)[LM],(#d1.#d)[LMN],(f1.#c)[LM],(g1.c)[LM],(#g1.#A-1)[LM],#a1[LM],(g1.e)[LMN],(f1.f)[LM],(e1.g)[LM],(f1.f)[LMN],(g1.e)[LM],(#g1.d)[LM],(#a1.c)[LM],c2[LM],(#g1.f)[LMN],(g1.g)[LM],(f1.#g)[LM],(g1.g)[LMN],(#g1.f)[LM],(#a1.#d)[LM],(c2.d)[LM],#c2[LM],(e1.c)[LMN],#c2[LM],(c2.C-1)[LM],#a1[LMN],#g1[LM],g1[LM],(f1.c)[LM],e1[LM],(f1.#c)[KLN],(g1.e)[KLN],(#g1.f)[KL],b1[KL],c2[LMN],e[LM],f[LM],g[LMN],#g[LM],b1[LM],c2[LM],d2[LM],#d2[KLN],#f[LM],f[LMN],#f[KL],(#c2.A-1)[LM],c2[LM],(#c2.#A-1)[KLN],e1[KLN],f1[KL],#G-1[KL],B-1[KLN],(#d1.c)[KLN],#f1[KL],(g1.#A-1)[LM],A-1[LM],#A-1[KLN],(f1.g)[LM],(e1.#A-1)[LMN],(f1.#G-1)[LM],G-1[LM],(d2.F-1)[LM],(f1.#G-1)[LM],(#d1.G-1)[LMN],d1[LM],(c1.c)[LM],#d1[LMN],(d1.f)[M],g[M],f[M],e[LM],(b1.f)[KL],c2[M],d2[M],c2[MN],b1[LM],(c2.e)[LM],d[LMN],c[LM],#A-1[LM],#G-1[LM],G-1[LM],F-1[JKM],(c1.A-1)[JK],(e1.c)[JKM],g1[KL],#A-1[LM],#G-1[LM],#A-1[KLN],(f1.c)[LM],e1[LMN],(f1.d)[KL],(g1.e)[KL],(#g1.f)[KLN],#a1[KLN],c2[KL],e[LM],d[LM],e[KLN],(#a1.f)[LM],#g1[LMN],(#a1.g)[KL],(c2.a)[KL],(d2.c1)[LMN],#a[LM],(e2.#g)[LM],g[LMN],(f2.#g)[KL],#c1[KL],#a[KLN],(e2.g)[LM],d2[LMN],(c2.c1)[LM],#a1[LM],(#g1.c)[LM],g1[LM],(#g1.f)[KLN],(b1.d)[KLN],(c2.#d)[KL],f[KL],g[LMN],b1[LM],c2[LM],d2[LMN],#d2[LM],#f[LM],g[LM],a[LM],#a[KLN],#c2[LM],c2[LMN],#c2[KL],(e1.#g)[LM],g[LM],(f1.#g)[KLN],B-1[KLN],c[KL],#d1[KL],#f1[KLN],(g1.#A-1)[KLN],c[KL],(f1.d)[LM],e1[LM],f1[KLN],(d2.c)[LM],(f1.B-1)[LMN],(#d1.c)[LM],d1[LM],(c1.a)[LM],(#d1.c)[LM],(d1.#A-1)[LMN];"],"id":2,"instruments":["piano","piano"],"alternatives":["",""]},{"bpm":300,"baseBeats":0.75,"scores":["mute[LM],mute[LM],mute[LMN],5<UV>,mute[LM],mute[KL],5<UV>,mute[LM],mute[LM],mute[LM],mute[LM],mute[LM],mute[LM],mute[K],mute[JKM],mute[JK],mute[JKM],mute[KL],mute[LM],mute[LM],mute[KLN],mute[LM],mute[LMN],mute[KL],mute[KL],mute[KLN],mute[KLN],mute[KL],mute[LM],mute[LM],mute[KLN],mute[LM],mute[LMN],mute[KL],mute[KL],mute[LM],mute[LM],mute[LM],mute[K],mute[KL],mute[KL],5<UV>,mute[LM],mute[LM],mute[LM],mute[LM],mute[LM],mute[LM],mute[LM],mute[LM],mute[LM],mute[LM],mute[LM],mute[LM],mute[LM],mute[LM],mute[LM],mute[LM],mute[LM],mute[LM],mute[LM],mute[LM],mute[LM],mute[LM],mute[LM],mute[LM],mute[LM],mute[LM],mute[LM],mute[LM],mute[LM],mute[LM],mute[LM],mute[LM],mute[LM],mute[LM],mute[LM],mute[LM],mute[LM],mute[LM],mute[LM],mute[KM],mute[KLN],mute[KLN],mute[KL],mute[KL],mute[LM],mute[LM],mute[LM],mute[LM],mute[LM],mute[LM],mute[LM],mute[LM],mute[LM],mute[LM],mute[LM],mute[KM],mute[KL],mute[LM],mute[LM],mute[KLN],5<UV>,mute[LM],mute[LM],mute[LM],mute[LM],mute[LM],mute[LM],mute[LM],mute[LM],mute[LM],mute[LM],mute[LM],mute[LM],mute[LM],mute[LM],mute[LM],mute[LM],mute[LM],mute[LM],mute[LM],mute[LM],mute[LM],mute[LM],mute[LM],mute[LM],mute[LM],mute[LM],mute[LM],mute[LM],mute[LM],mute[LM],mute[LM],mute[LM],mute[LM],mute[LM],mute[LM],mute[LM],mute[LM],mute[LM],mute[LM],mute[LM],mute[LM],mute[LM],mute[LM],mute[LM],mute[LM],mute[LM],mute[LM],mute[LM],mute[LM],mute[LM],mute[LM],mute[LM],mute[LM],mute[LM],mute[LM],mute[LM],mute[LM],mute[LM],mute[LM],mute[LM],mute[LM],mute[LM],mute[LM],mute[LM],mute[LM],mute[LM],mute[LM],mute[LM],mute[LM],mute[LM],mute[LM],mute[LM],mute[LM],mute[LM],mute[LM],mute[LM],mute[LM],mute[LM],mute[LM],mute[LM],mute[LM],mute[LM],mute[LM],mute[LM],mute[LM],mute[LM],mute[LM],mute[LM],mute[LM],mute[LM],mute[LM],mute[KMN],mute[KL],mute[LM],mute[LM],mute[KLN],mute[LM],mute[LM],mute[LM],mute[LM],mute[LM],mute[LM],mute[LM],mute[LM],mute[LM],mute[LM],mute[LM],mute[LM],mute[LM],mute[LM],mute[LM],mute[LM],mute[LM],mute[LM],mute[LM],mute[LM],mute[LM],mute[LM],mute[LM],mute[LM],mute[LM],mute[LM],mute[LM],mute[LM],mute[LM],mute[LM],mute[LM],mute[LM],mute[LM],mute[LM],mute[LM],mute[LM],mute[LM],mute[LM],mute[LM],mute[LM],mute[LM],mute[LM],mute[LM],mute[LM],mute[LM],mute[LM],mute[LM],mute[LM],mute[LM],mute[LM],mute[LM],mute[LM],mute[LM],mute[LM],mute[LM],mute[LM],mute[LM],mute[LM],mute[LM],mute[LM],mute[LM],mute[LM],mute[LM],mute[LM],mute[LM],mute[LM],mute[LM],mute[LM],mute[LM],mute[LM],mute[LM],mute[LM],mute[LM],mute[LM],mute[LM],mute[LM],mute[LM],mute[LM],mute[LM],mute[LM],mute[LM],mute[LM],mute[LM],mute[LM],mute[LM],mute[LM],mute[LM],mute[LM],mute[LM],mute[LM],mute[LM],mute[LM],mute[LM],mute[LM],mute[LM],mute[LM],mute[LM],mute[LM],mute[LM],mute[LM],mute[LM],mute[LM],mute[LM],mute[LM],mute[LM],mute[LM],mute[LM],mute[LM],mute[LM],mute[LM],mute[LM],mute[LM],mute[LM],mute[LM],mute[LM],mute[LM],mute[LM],mute[LM],mute[LM],mute[LM],mute[LM],mute[LM],mute[LM],mute[LM],mute[LM],mute[LM],mute[LM],mute[LM],mute[LM],mute[LM],mute[LM],mute[LM],mute[LM],mute[LM],mute[LM],mute[LM],mute[KMN],mute[K],mute[LMN],mute[IN],5<UV>,5<UV>,5<UV>,5<UV>,mute[KMN],mute[HIJ];","A-1[LM],(g1.G-1)[LM],#A-1[LMN],(c2.A-1)[M],d2[M],c2[M],b1[LM],(c2.d)[KL],g[M],a[M],g[MN],#f[LM],(#a1.g)[LM],a1[LMN],g1[LM],f1[LM],#d1[LM],d1[LM],c1[JKM],(#d1.G-1)[JK],(g1.B-1)[JKM],d[KL],f1[LM],#d1[LM],f1[KLN],(g1.c)[LM],B-1[LMN],(a1.c)[KL],(b1.d)[KL],(c2.#d)[KLN],f[KLN],g[KL],b1[LM],a1[LM],b1[KLN],(c2.f)[LM],e[LMN],(d2.f)[KL],(#d2.g)[KL],(g2.a)[LMN],f2[LM],(#d2.b)[LM],d2[LMN],(#d2.c1)[KL],(c2.#g)[KL],(d2.g)[L],c2[MN],(d2.f)[LM],#d[LM],f[LMN],(c2.g)[LM],b1[LM],(a1.G-1)[LM],b1[LM],(c2.c)[LMN],a1[LM],g1[LM],f1[LMN],e1[LM],d1[LM],c1[LM],#a[LM],(f1.a)[LMN],f1[LM],e1[LM],d1[LMN],(a1.c1)[LM],#a[LM],a[LM],g[LM],(c2.f)[LMN],#a[LM],a[LM],g[LMN],f[LM],#d[LM],(#a1.d)[LM],(a1.c)[LM],(#a1.d)[LMN],f[LM],(c2.e)[LM],d[LMN],(d2.c)[LM],#A-1[LM],(e2.A-1)[LM],G-1[LM],(f2.A-1)[KLN],(c2.F-1)[KLN],f2[KL],a2[KL],(g2.c)[LMN],f2[LM],e2[LM],d2[LMN],(c2.e)[LM],#a1[LM],a1[LM],g1[LM],(a1.f)[LMN],c2[LM],f1[LM],a1[LMN],d2[KL],f[LM],e[LM],f[KLN],(c2.g)[M],d2[M],c2[M],b1[LMN],(c2.a)[LM],e2[LM],(d2.b)[LM],f2[LM],(e2.c1)[LMN],d2[LM],(c2.g)[LM],b1[LMN],(a1.c1)[LM],c2[LM],(g1.e1)[LM],c2[LM],(f1.d1)[LMN],(e2.c1)[LM],(d2.b)[LM],(c2.a)[LMN],(b1.g)[LM],(d2.f)[LM],(g1.e)[LM],(b1.d)[LM],(c2.e)[LMN],g[LM],c[LM],e[LMN],a[LM],e2[LM],a1[LM],c2[LM],f1[LMN],c1[LM],f[LM],a[LMN],d[LM],a1[LM],d1[LM],f1[LM],#a1[LMN],f[LM],#A-1[LM],d[LMN],g[LM],d2[LM],g1[LM],#a1[LM],e1[LMN],#a[LM],e[LM],g[LMN],c[LM],g1[LM],c1[LM],e1[LM],a1[LMN],(c2.e)[LM],(f1.A-1)[LM],(a1.c)[LMN],(d1.f)[LM],(f1.a)[LM],(#a.d)[LM],(d1.f)[LM],(g1.#A-1)[LMN],(#a1.d)[LM],(e1.G-1)[LM],(g1.#A-1)[LMN],(c1.e)[LM],(e1.g)[LM],(a.c)[LM],(c1.e)[LM],(f1.A-1)[LMN],(a1.c)[LM],(d1.F-1)[LM],(f1.A-1)[LMN],(#a1.d)[LM],(d2.f)[LM],(g1.#A-1)[LM],(#a1.d)[LM],(c1.e)[LMN],g[LM],c[LM],e[LMN],(e1.g)[LM],#a[LM],e[LM],g[LM],(f1.a)[LMN],c1[LM],f[LM],a[LMN],d1[KL],f1[LM],e1[LM],f1[KLN],(g1.c1)[LM],#a[LMN],(a1.c1)[LM],#d1[LM],(#a1.d1)[LM],f1[LM],(c2.#d1)[LMN],d1[LM],(f1.#d1)[LM],c1[LMN],(#a1.d1)[LM],f1[LM],(d2.#a)[LM],d1[LM],(c2.#d)[LMN],(#a1.d1)[LM],(a1.c1)[LM],(g1.#a)[LMN],(f1.a)[LM],(#d1.c1)[LM],(d1.f)[LM],(c1.a)[LM],(d1.#A-1)[LMN],#a[LM],f1[LM],d1[LMN],#a1[LM],G-1[LM],d[LM],#A-1[LM],g[LMN],d2[LM],g1[LM],#a1[LMN],e1[LM],#a[LM],e[LM],g[LM],c[LMN],c1[LM],g1[LM],e1[LMN],c2[LM],A-1[LM],e[LM],c[LM],a[LMN],e2[LM],a1[LM],c2[LMN],f1[LM],c1[LM],f[LM],a[LM],d[LMN],d1[LM],a1[LM],f1[LMN],d2[LM],(a1.f)[LM],(f2.d)[LM],(d2.f)[LM],(#a1.g)[LMN],(g1.#a)[LM],(d2.d)[LM],(#a1.g)[LMN],(g2.#A-1)[LM],(d2.d)[LM],(#a2.G-1)[LM],(g2.#A-1)[LM],(e2.c)[LMN],(c2.e)[LM],(g2.G-1)[LM],(e2.c)[LMN],(#a2.E-1)[LM],(g2.G-1)[LM],(e2.C-1)[LM],(c3.E-1)[LM],(a2.F-1)[LMN],c3[LM],f2[LM],a2[LMN],(c2.A-1)[LM],f2[LM],#d2[LM],d2[LM],(#d2.c)[LMN],g2[LM],c2[LM],#d2[LMN],a1[LM],#d2[LM],(d2.#A-1)[LM],(c2.A-1)[LM],(d2.#A-1)[LMN],#a1[LM],(e2.c)[LM],#a1[LMN],(f2.d)[LM],#a1[LM],(g2.e)[LM],#a1[LM],(a1.f)[LMN],g2[LM],(f2.c)[LM],e2[LMN],(d2.f)[LM],f2[LM],(c2.a)[LM],f2[LM],(#a1.g)[LMN],(a2.f)[LM],(g2.e)[LM],(f2.d)[LMN],(e2.c)[LM],(g2.#A-1)[LM],(c2.A-1)[LM],(e2.G-1)[LM],(f2.A-1)[LMN],(c2.c)[LM],(a2.F-1)[LM],(f2.A-1)[LMN],(c2.c)[LM],(a1.f)[LM],(f2.A-1)[LM],(c2.c)[LMN],(a1.f)[LMN],(f1.a)[LM],(c2.c)[LM],(a1.f)[LMN],(f1.a)[LMN],c1[LM],(a1.f)[K],(f1.a)[LMN],c1[JKLM],(#a2.c)[L],a2[L],g2[M],a2[MN],g2[M],a2[L],g2[L],f2[L],g2[KMN],(f2.f)[HIJ];"],"id":3,"instruments":["piano","piano"],"alternatives":["",""]}],"audition":{"start":[0,0],"end":[2,345]}}