{"baseBpm":240,"musics":[{"id":1,"baseBeats":0.5,"scores":["5<(c.e.g)[M],(c.e.g)[M]>,5<(c.e.g)[M],(c.e.g)[M]>,5<(c.e.g)[M],(c.e.g)[M]>,5<(c.e.g)[M],(c.e.g)[M]>,5<(c.e.g)[M],(c.e.g)[M]>,5<(c.e.g)[M],(c.e.g)[M]>,5<(c.e.g)[M],(c.e.g)[M]>,5<(c.e.g)[M],(c.e.g)[M]>,5<(c.e.g)[M],(c.e.g)[M]>,5<(c.e.g)[M],(c.e.g)[M]>,5<(c.e.g)[M],(c.e.g)[M]>,5<(c.e.g)[M],(c.e.g)[M]>,5<(c.e.g)[M],(c.e.g)[M]>,5<(c.e.g)[M],(c.e.g)[M]>,5<(c.e.g)[M],(c.e.g)[M]>,5<(c.e.g)[M],(c.e.g)[M]>,","5<(c.e.g)[M],(c.e.g)[M]>,5<(c.e.g)[M],(c.e.g)[M]>,5<(c.e.g)[M],(c.e.g)[M]>,5<(c.e.g)[M],(c.e.g)[M]>,5<(c.e.g)[M],(c.e.g)[M]>,5<(c.e.g)[M],(c.e.g)[M]>,5<(c.e.g)[M],(c.e.g)[M]>,5<(c.e.g)[M],(c.e.g)[M]>,5<(c.e.g)[M],(c.e.g)[M]>,5<(c.e.g)[M],(c.e.g)[M]>,5<(c.e.g)[M],(c.e.g)[M]>,5<(c.e.g)[M],(c.e.g)[M]>,5<(c.e.g)[M],(c.e.g)[M]>,5<(c.e.g)[M],(c.e.g)[M]>,5<(c.e.g)[M],(c.e.g)[M]>,5<(c.e.g)[M],(c.e.g)[M]>,"]},{"id":2,"baseBeats":0.5,"scores":["3<(c.e.g)[L]>,3<(c.e.g)[L]>,3<(c.e.g)[L]>,3<(c.e.g)[L]>,3<(c.e.g)[L]>,3<(c.e.g)[L]>,3<(c.e.g)[L]>,3<(c.e.g)[L]>,3<(c.e.g)[L]>,3<(c.e.g)[L]>,3<(c.e.g)[L]>,3<(c.e.g)[L]>,3<(c.e.g)[L]>,3<(c.e.g)[L]>,3<(c.e.g)[L]>,3<(c.e.g)[L]>,3<(c.e.g)[L]>,3<(c.e.g)[L]>,3<(c.e.g)[L]>,3<(c.e.g)[L]>,3<(c.e.g)[L]>,3<(c.e.g)[L]>,3<(c.e.g)[L]>,3<(c.e.g)[L]>,3<(c.e.g)[L]>,3<(c.e.g)[L]>,3<(c.e.g)[L]>,3<(c.e.g)[L]>;","3<(c.e.g)[L]>,3<(c.e.g)[L]>,3<(c.e.g)[L]>,3<(c.e.g)[L]>,3<(c.e.g)[L]>,3<(c.e.g)[L]>,3<(c.e.g)[L]>,3<(c.e.g)[L]>,3<(c.e.g)[L]>,3<(c.e.g)[L]>,3<(c.e.g)[L]>,3<(c.e.g)[L]>,3<(c.e.g)[L]>,3<(c.e.g)[L]>,3<(c.e.g)[L]>,3<(c.e.g)[L]>,3<(c.e.g)[L]>,3<(c.e.g)[L]>,3<(c.e.g)[L]>,3<(c.e.g)[L]>,3<(c.e.g)[L]>,3<(c.e.g)[L]>,3<(c.e.g)[L]>,3<(c.e.g)[L]>,3<(c.e.g)[L]>,3<(c.e.g)[L]>,3<(c.e.g)[L]>,3<(c.e.g)[L]>,"]},{"id":3,"baseBeats":0.5,"scores":["8<c[M],e[M],g[M],c[M],e[M],g[M],c[M],e[M],g[M]>,8<c[M],e[M],g[M],c[M],e[M],g[M],c[M],e[M],g[M]>,8<c[M],e[M],g[M],c[M],e[M],g[M],c[M],e[M],g[M]>,8<c[M],e[M],g[M],c[M],e[M],g[M],c[M],e[M],g[M]>,","8<c[M],e[M],g[M],c[M],e[M],g[M],c[M],e[M],g[M]>,8<c[M],e[M],g[M],c[M],e[M],g[M],c[M],e[M],g[M]>,8<c[M],e[M],g[M],c[M],e[M],g[M],c[M],e[M],g[M]>,8<c[M],e[M],g[M],c[M],e[M],g[M],c[M],e[M],g[M]>;"]}]}