{"baseBpm":228,"musics":[{"bpm":228,"baseBeats":0.75,"scores":["TU,TU,TU,TU,TU,TU,TU,TU,TU,TU,TU,TU,TU,TU,TU,TU,TU,TU,TU,TU,TU,TU,TU,TU,TU,TU,TU,TU,TU,SV,5<UV>,TU,TU,TU,TU,TU,TU,TU,TU,TU,TU,TU,TU,TU,TU,TU,TU,TU,TU,UV,UV,UV,UV,UV,UV,5<UV>,5<UV>,TU,UV,5<UV>,TU,TU,UV,UV,UV,UV,UV,UV,UV,UV,UV,UV,UV,UV,UV,UV,UV,UV,5<UV>,5<UV>,UV,UV,UV,UV,UV,UV,UV,UV,UV,UV,UV,UV,UV,UV,5<UV>,5<UV>,UV,UV,UV,UV,UV,UV,UV,UV,UV,UV,UV,UV,UV,UV,5<UV>,5<UV>,UV,UV,UV,UV,UV,UV,5<UV>,5<UV>,UV,UV,UV,UV,UV,UV,UV,UV,UV,UV,UV,UV,UV,UV,UV,UV,UV,UV,UV,UV,UV,UV,5<UV>,5<UV>,UV,UV,UV,UV,UV,UV,UV,UV,UV,UV,UV,UV,UV,UV,UV,UV,UV,UV,UV,UV,UV,UV,UV,UV,UV,UV,UV,UV,UV,UV,UV,UV,UV,UV,UV,UV,UV,UV,UV,UV,UV,UV,UV,UV,UV,UV,UV,UV,UV,UV,UV,UV,UV,UV,UV,UV,UV,UV,UV,UV,UV,UV,ST,TU,TU,TU,TU,TU,TU,TU,TU,TU,TU,TU,TU,TU,TU,TU,TU,TU,TU,TU,TU,TU,TU,TU,TU,TU,TU,TU,TU,TU,TU,SV,5<UV>,TU,TU,TU,TU,TU,TU,TU,TU,TU,TU,TU,TU,TU,TU,TU,TU,TU,TU,UV,UV,UV,UV,UV,UV,5<UV>,5<UV>,TU,UV,5<UV>,TU,TU,UV,UV,UV,UV,UV,UV,UV,UV,UV,UV,UV,UV,UV,UV,UV,UV,5<UV>,5<UV>,UV,UV,UV,UV,UV,","d1[KL],#a1[KL],(#a.d1.g1)[KL],(a.c1.#f1)[KL],(g.#a.g1)[KL],(#f.a.d1.c2)[KL],(d.#f)[KL],(e.g)[KL],(#f.a)[KL],(g.#a.#a1)[KL],(#a.d1.g1)[KL],(a.c1.#f1)[KL],(g.#a.g1)[KL],(c.g1.#d2)[KL],#d[KL],g[KL],c1[KL],(#a.d2)[KL],#f2[KL],g2[KL],(#a.d1.d2)[KL],(#f.d1.c2)[KL],#g2[KL],a2[KL],(#f.d1.c2)[KL],(g.d1.#a1)[KL],g2[KL],(c.c1.a1)[KL],#d2[KL],(d.#a.g1)[JM],a1[MN],g1[MN],(a.#f1)[KL],d1[KL],#a1[KL],(#a.d1.g1)[KL],(a.c1.#f1)[KL],(g.#a.g1)[KL],(#f.a.d1.c2)[KL],(d.#f)[KL],(e.g)[KL],(#f.a)[KL],(g.#a.#a1)[KL],(#a.d1.g1)[KL],(a.c1.#f1)[KL],(g.#a.g1)[KL],(c.#d2)[KL],#d[KL],g[KL],(a.c.#d2)[KL],(#a.d)[LM],d2[LM],f2[LM],e2[LM],g2[LM],f2[LM],(f.d.#d2)[LM],d2[MN],c2[N],d2[N],#d2[N],(g.#d.d2)[KL],(c1.c2)[KN],b1[N],c2[N],d2[N],(g.e.c2)[KL],(c1.#a1)[KM],c2[N],(d2.#d2)[N],(f.c1.#a1)[LM],a1[LM],g1[LM],f1[LM],e1[LM],f1[LM],g1[LM],f1[LM],(a.#d2)[LM],f1[LM],(c1.a1)[LM],f1[LM],(#d1.a1)[LM],f1[LM],(c1.a1)[LM],f1[LM],(d1.#a1)[LM],f1[MN],c2[N],#a1[N],a1[N],(#a.#a1)[LM],(f1.d2)[LM],(d1.f2)[LM],f1[LM],(#a.f2)[LM],f1[LM],(a.#d3)[LM],f1[LM],(c1.a2)[LM],f1[LM],(#d1.a2)[LM],f1[LM],(c1.a2)[LM],f1[LM],(d1.#a2)[LM],f1[MN],c3[N],#a2[N],a2[N],(#a.#a2)[LM],(f1.d3)[LM],(d1.f3)[LM],f1[LM],(#a.f1)[LM],f1[LM],(a.#d2)[LM],f1[LM],(c1.a1)[LM],f1[LM],(#d1.a1)[LM],f1[LM],(c1.a1)[LM],f1[LM],(d1.#a1)[LM],f1[MN],c2[N],#a1[N],a1[N],(#a.#a1)[LM],(f1.d2)[LM],(#g.d2)[LM],(f1.#a1)[LM],(#a.c2)[LM],(f1.d2)[LM],(g.#d2)[LM],#d1[MN],f2[N],#d2[N],d2[N],(#a.#d2)[LM],(#d1.f2)[LM],(#d.g2)[LM],(#d1.a2)[LM],(#a.#a2)[LM],(#d1.g2)[LM],(f.e2)[LM],(d1.f2)[LM],(#a.g2)[LM],(d1.f2)[LM],(f.f2)[LM],(#d1.#d2)[LM],(a.d2)[LM],(#d1.c2)[LM],(#a.d1.#c2)[LM],d2[LM],#d2[LM],d2[LM],f2[LM],#d2[LM],d2[LM],c2[LM],(d1.#a1)[LM],f1[MN],c2[N],#a1[N],a1[N],(#a.#a1)[LM],(f1.c2)[LM],(#g.d2)[LM],(f1.#a1)[LM],(#a.c2)[LM],(f1.d2)[LM],(g.#d2)[LM],(#d1.f2)[LM],(#a.g2)[LM],(#d1.a2)[LM],(#d.c3)[LM],(#d1.#a2)[LM],(#a.a2)[LM],(#d1.g2)[LM],(d.g2)[LM],(d1.f2)[LM],(#a.e2)[LM],(d1.f2)[LM],(#d.a2)[LM],(c1.g2)[LM],(g.f2)[LM],(c1.#d2)[LM],(f.#d2)[LM],(d1.d2)[LM],(a.#c2)[LM],(d1.d2)[LM],(f.f2)[LM],(#d1.#d2)[LM],(a.d2)[LM],(#d1.c2)[LM],(#a.d1.#a1)[LM],f1[LM],e1[LM],f1[LM],g1[LM],f1[LM],(#d1.c2)[LM],(d1.d2)[LM],(c1.#d2)[LM],f1[LM],(#d1.a1)[LM],f1[LM],(f.c1.a1)[LM],f1[LM],(#d1.a1)[LM],f1[LM],(#a.d1.#a1)[LM],f1[LM],e1[LM],f1[LM],g1[LM],f1[LM],(#d1.c2)[LM],(d1.d2)[LM],(c1.#d2)[LM],f1[LM],(#d1.a1)[LM],f1[LM],(f.c1.a1)[LM],f1[LM],(#d1.a1)[LM],f1[LM],(#a.#d1.a1.c2)[JK],(d1.#a1)[KL],d1[KL],#a1[KL],(#a.d1.g1)[KL],(a.c1.#f1)[KL],(g.#a.g1)[KL],(#f.a.d1.c2)[KL],(d.#f)[KL],(e.g)[KL],(#f.a)[KL],(g.#a.#a1)[KL],(#a.d1.g1)[KL],(a.c1.#f1)[KL],(g.#a.g1)[KL],(c.g1.#d2)[KL],#d[KL],g[KL],c1[KL],(#a.d2)[KL],#f2[KL],g2[KL],(#a.d1.d2)[KL],(#f.d1.c2)[KL],#g2[KL],a2[KL],(#f.d1.c2)[KL],(g.d1.#a1)[KL],g2[KL],(c.c1.a1)[KL],#d2[KL],(d.#a.g1)[JM],a1[MN],g1[MN],(a.#f1)[KL],d1[KL],#a1[KL],(#a.d1.g1)[KL],(a.c1.#f1)[KL],(g.#a.g1)[KL],(#f.a.d1.c2)[KL],(d.#f)[KL],(e.g)[KL],(#f.a)[KL],(g.#a.#a1)[KL],(#a.d1.g1)[KL],(a.c1.#f1)[KL],(g.#a.g1)[KL],(c.#d2)[KL],#d[KL],g[KL],(a.c.#d2)[KL],(#a.d)[LM],d2[LM],f2[LM],e2[LM],g2[LM],f2[LM],(f.d.#d2)[LM],d2[MN],c2[N],d2[N],#d2[N],(g.#d.d2)[KL],(c1.c2)[KN],b1[N],c2[N],d2[N],(g.e.c2)[KL],(c1.#a1)[KM],c2[N],(d2.#d2)[N],(f.c1.#a1)[LM],a1[LM],g1[LM],f1[LM],e1[LM],f1[LM],g1[LM],f1[LM],(a.#d2)[LM],f1[LM],(c1.a1)[LM],f1[LM],(#d1.a1)[LM],f1[LM],(c1.a1)[LM],f1[LM],(d1.#a1)[LM],f1[MN],c2[N],#a1[N],a1[N],(#a.#a1)[LM],(f1.d2)[LM],(d1.f2)[LM],f1[LM],(#a.f2)[LM],"],"id":1},{"bpm":228,"baseBeats":0.75,"scores":["UV,UV,UV,UV,UV,UV,UV,UV,UV,5<UV>,5<UV>,UV,UV,UV,UV,UV,UV,UV,UV,UV,UV,UV,UV,UV,UV,5<UV>,5<UV>,UV,UV,UV,UV,UV,UV,5<UV>,5<UV>,UV,UV,UV,UV,UV,UV,UV,UV,UV,UV,UV,UV,UV,UV,UV,UV,UV,UV,UV,UV,UV,UV,5<UV>,5<UV>,UV,UV,UV,UV,UV,UV,UV,UV,UV,UV,UV,UV,UV,UV,UV,UV,UV,UV,UV,UV,UV,UV,UV,UV,UV,UV,UV,UV,UV,UV,UV,UV,UV,UV,UV,UV,UV,UV,UV,UV,UV,UV,UV,UV,UV,UV,UV,UV,UV,UV,UV,UV,UV,UV,UV,UV,UV,UV,UV,UV,UV,UV,ST,TU,5<UV>,5<UV>,TU,TU,TU,5<UV>,5<UV>,TU,TU,TU,5<UV>,5<UV>,TU,TU,TU,TU,TU,TU,TU,TU,TU,TU,UV,UV,UV,UV,TU,TU,UV,UV,UV,UV,TU,UV,UV,UV,UV,UV,UV,UV,UV,UV,UV,UV,UV,UV,UV,TU,TU,UV,5<UV>,5<UV>,5<UV>,UV,UV,TU,UV,5<UV>,5<UV>,5<UV>,UV,UV,TU,UV,5<UV>,5<UV>,5<UV>,UV,UV,UV,UV,UV,UV,UV,UV,UV,UV,UV,UV,UV,UV,UV,UV,UV,UV,UV,UV,UV,UV,UV,UV,UV,UV,UV,UV,UV,UV,UV,UV,UV,UV,UV,UV,UV,UV,UV,UV,UV,UV,UV,UV,UV,UV,UV,UV,UV,UV,UV,UV,UV,UV,UV,UV,UV,UV,UV,UV,UV,UV,UV,UV,UV,UV,UV,UV,UV,UV,UV,UV,UV,UV,UV,UV,UV,UV,UV,UV,UV,UV,UV,UV,UV,UV,UV,UV,UV,UV,UV,UV,UV,UV,UV,UV,UV,UV,UV,UV,UV,UV,UV,UV,UV,UV,UV,UV,UV,UV,UV,UV,UV,UV,UV,UV,UV,UV,UV,UV,UV,UV,UV,UV,UV,UV,UV,UV,UV,UV,UV,UV,UV,UV,UV,UV,UV,UV,UV,UV,UV,UV,UV,UV,5<UV>,UV,TU,TU,TU,TU,TU,TU,TU,TU,TU,TU,TU,TU,TU,TU,TU,TU,TU,TU,TU,TU,TU,TU,TU,","f1[LM],(a.#d3)[LM],f1[LM],(c1.a2)[LM],f1[LM],(#d1.a2)[LM],f1[LM],(c1.a2)[LM],f1[LM],(d1.#a2)[LM],f1[MN],c3[N],#a2[N],a2[N],(#a.#a2)[LM],(f1.d3)[LM],(d1.f3)[LM],f1[LM],(#a.f1)[LM],f1[LM],(a.#d2)[LM],f1[LM],(c1.a1)[LM],f1[LM],(#d1.a1)[LM],f1[LM],(c1.a1)[LM],f1[LM],(d1.#a1)[LM],f1[MN],c2[N],#a1[N],a1[N],(#a.#a1)[LM],(f1.d2)[LM],(#g.d2)[LM],(f1.#a1)[LM],(#a.c2)[LM],(f1.d2)[LM],(g.#d2)[LM],#d1[MN],f2[N],#d2[N],d2[N],(#a.#d2)[LM],(#d1.f2)[LM],(#d.g2)[LM],(#d1.a2)[LM],(#a.#a2)[LM],(#d1.g2)[LM],(f.e2)[LM],(d1.f2)[LM],(#a.g2)[LM],(d1.f2)[LM],(f.f2)[LM],(#d1.#d2)[LM],(a.d2)[LM],(#d1.c2)[LM],(#a.d1.#c2)[LM],d2[LM],#d2[LM],d2[LM],f2[LM],#d2[LM],d2[LM],c2[LM],(d1.#a1)[LM],f1[MN],c2[N],#a1[N],a1[N],(#a.#a1)[LM],(f1.c2)[LM],(#g.d2)[LM],(f1.#a1)[LM],(#a.c2)[LM],(f1.d2)[LM],(g.#d2)[LM],(#d1.f2)[LM],(#a.g2)[LM],(#d1.a2)[LM],(#d.c3)[LM],(#d1.#a2)[LM],(#a.a2)[LM],(#d1.g2)[LM],(d.g2)[LM],(d1.f2)[LM],(#a.e2)[LM],(d1.f2)[LM],(#d.a2)[LM],(c1.g2)[LM],(g.f2)[LM],(c1.#d2)[LM],(f.#d2)[LM],(d1.d2)[LM],(a.#c2)[LM],(d1.d2)[LM],(f.f2)[LM],(#d1.#d2)[LM],(a.d2)[LM],(#d1.c2)[LM],(#a.d1.#a1)[LM],f1[LM],e1[LM],f1[LM],g1[LM],f1[LM],(#d1.c2)[LM],(d1.d2)[LM],(c1.#d2)[LM],f1[LM],(#d1.a1)[LM],f1[LM],(f.c1.a1)[LM],f1[LM],(#d1.a1)[LM],f1[LM],(#a.d1.#a1)[LM],f1[LM],e1[LM],f1[LM],g1[LM],f1[LM],(#d1.c2)[LM],(d1.d2)[LM],(c1.#d2)[LM],f1[LM],(#d1.a1)[LM],f1[LM],(f.c1.a1)[LM],f1[LM],(#d1.a1)[LM],f1[LM],(#a.#d1.a1.c2)[JK],(d1.#a1)[KL],(#A-1.#a)[MN],(c.c1)[MN],(#A-1.#a)[MN],(c.c1)[MN],(f.f1)[KL],(#A-1.#a)[KL],(#A-1.#a)[KL],(#A-1.#a)[MN],(c.c1)[MN],(#A-1.#a)[MN],(c.c1)[MN],(f.f1)[KL],(#G-1.#g)[KL],(#G-1.#g)[KL],(#G-1.#g)[MN],(#A-1.#a)[MN],(#G-1.#g)[MN],(#A-1.#a)[MN],(G-1.g)[KL],(#A-1.#a)[KL],(#d.#d1)[KL],(g.g1)[KL],(#g.#G-1.f1.c1)[KL],(f.#g1)[KL],(f.#A-1.d1.#g)[KL],(d.#a)[KL],(#D-1.#d.g.#a.#d1)[KL],(#d1.g1)[KL],(#d1.g1)[LM],g2[LM],f2[LM],#d2[LM],d2[KL],(f1.#g1)[KL],(f1.#g1)[LM],#g2[LM],g2[LM],f2[LM],#d2[KL],(g1.#a1)[LM],#d3[LM],(g1.#a1.d3)[LM],#d3[LM],(g1.#a1.d3)[LM],c3[LM],(#g1.c2.b2)[LM],c3[LM],#a2[LM],#g2[LM],(#a1.d2.g2)[LM],f2[LM],c3[LM],#a2[LM],#g2[KL],(#d1.#a1.g2)[KL],(#d1.g1)[LM],g2[MN],f2[MN],#g2[MN],g2[MN],f2[MN],#d2[N],f2[M],#d2[LM],d2[LM],(f1.#g1.d2)[KL],(f1.#g1)[LM],#g2[MN],g2[MN],#a2[MN],#g2[MN],g2[MN],f2[N],g2[M],f2[LM],#d2[LM],(g1.#a1.#d2)[KL],(g1.#a1)[LM],#d3[MN],d3[MN],(g1.#a1.f3)[MN],#d3[MN],d3[MN],c3[MN],(#g1.c2.b2)[LM],c3[LM],#a2[LM],#g2[LM],(#a.f1.#g1.g2)[LM],f2[LM],#g2[LM],d2[LM],(#d1.g1.#d2)[LM],#a1[LM],a1[LM],#a1[LM],c2[LM],#a1[LM],(#g1.f2)[LM],(g1.g2)[LM],(f1.#g2)[LM],#a1[LM],(#g1.d2)[LM],#a1[LM],(#a.f1.d2)[LM],#a1[LM],(#g1.d2)[LM],#a1[LM],(#d1.#d2)[LM],g1[LM],#f1[LM],g1[LM],#g1[LM],g1[LM],(f1.d2)[LM],(#d1.#d2)[LM],(d1.f2)[LM],g1[LM],(f1.b1)[LM],g1[LM],(g.d1.b1)[LM],g1[LM],(f1.b1)[LM],g1[LM],(c1.c2)[LM],d1[LM],#d1[LM],d1[LM],c1[LM],#a[LM],(a.a1.a2)[LM],(g.#a1.#a2)[LM],(#f.c2.c3)[LM],d1[LM],(a.#f1.#f2)[LM],d1[LM],(c1.#f1.#f2)[LM],d1[LM],(a.#f1.#f2)[LM],d1[LM],(#a.g1.g2)[LM],d1[LM],g[LM],d1[LM],(#f.a1.a2)[LM],d1[LM],a[LM],d1[LM],(g.c2.c3)[LM],d1[LM],(#a.#a1.#a2)[LM],d1[LM],(#d.a1.a2)[LM],#c1[LM],(g.g1.g2)[LM],#c1[LM],(d.#f1.#f2)[LM],d1[LM],#f[LM],d1[LM],a[LM],(d1.d2)[LM],(#f.#c2)[LM],(d1.d2)[LM],(d.#a1.g2)[LM],d1[LM],g[LM],d1[LM],#a[LM],(d1.d2)[LM],(g.#c2)[LM],(d1.d2)[LM],(d.a1)[LM],d1[LM],#f[LM],d1[LM],a[LM],(d1.d2)[LM],(#f.#c2)[LM],(d1.d2)[LM],(d.#a1.g2)[LM],d1[LM],g[LM],d1[LM],#a[LM],(d1.d2)[LM],(g.#c2)[LM],(d1.d2)[LM],(d.a1)[LM],d1[LM],#f[LM],d1[LM],(d.b1)[LM],d1[LM],#g[LM],d1[LM],(d.c2)[LM],d1[LM],#g[LM],d1[LM],a[LM],d1[LM],(g.#a1)[LM],d1[LM],(d.a1)[LM],d1[LM],(#f.a2)[LM],d1[LM],(d.b1)[LM],d1[LM],(#g.b2)[LM],d1[LM],(d.c2)[LM],d1[LM],(#g.c3)[LM],d1[LM],a[LM],d1[LM],(g.#a1)[LM],d1[LM],(d.a1)[LM],d1[LM],(#f.a2)[LM],d1[LM],(d.b1)[LM],d1[LM],(#g.b2)[LM],d1[LM],(d.c2)[MN],a[MN],d1[LM],c3[KL],#c2[KL],#c3[KL],d2[KL],(#a.d1.g1)[KL],(a.c1.#f1)[KL],(g.#a.g1)[KL],(#f.a.d1.c2)[KL],(d.#f)[KL],(e.g)[KL],(#f.a)[KL],(g.#a.#a1)[KL],(#a.d1.g1)[KL],(a.c1.#f1)[KL],(g.#a.g1)[KL],(c.g1.#d2)[KL],#d[KL],g[KL],c1[KL],(#a.d2)[KL],#f2[KL],g2[KL],(#a.d1.d2)[KL],"],"id":2},{"bpm":228,"baseBeats":0.75,"scores":["TU,TU,TU,TU,TU,TU,TU,TU,SV,5<UV>,TU,TU,UV,UV,UV,UV,UV,UV,UV,UV,UV,UV,UV,UV,UV,UV,UV,UV,UV,UV,UV,UV,UV,UV,UV,UV,UV,UV,UV,UV,UV,UV,UV,UV,UV,UV,UV,UV,UV,UV,UV,UV,UV,UV,UV,UV,UV,UV,UV,UV,UV,UV,UV,UV,UV,UV,UV,UV,UV,UV,UV,UV,UV,UV,UV,UV,UV,UV,UV,UV,UV,UV,UV,UV,5<UV>,5<UV>,UV,UV,UV,UV,UV,UV,UV,UV,UV,UV,UV,UV,UV,UV,5<UV>,5<UV>,UV,UV,UV,UV,UV,UV,UV,UV,UV,UV,UV,UV,UV,UV,5<UV>,5<UV>,UV,UV,UV,UV,UV,UV,5<UV>,5<UV>,UV,UV,UV,UV,UV,UV,UV,UV,UV,UV,UV,UV,UV,UV,UV,5<UV>,5<UV>,UV,UV,UV,UV,UV,5<UV>,5<UV>,UV,UV,UV,UV,UV,UV,5<UV>,5<UV>,UV,UV,UV,UV,UV,UV,UV,UV,UV,UV,5<UV>,5<UV>,UV,UV,UV,UV,UV,UV,UV,UV,UV,UV,UV,UV,UV,UV,UV,UV,UV,UV,UV,UV,UV,UV,UV,UV,UV,UV,UV,UV,UV,UV,UV,UV,UV,UV,UV,UV,UV,UV,UV,UV,UV,UV,TU,TU,TU,TU,TU,TU,TU,TU,TU,TU,TU,TU,TU,TU,TU,TU,TU,TU,TU,TU,TU,TU,TU,TU,TU,TU,TU,TU,TU,TU,TU,TU,TU,TU,TU,TU,TU,TU,TU,TU,TU,TU,TU,TU,TU,TU,TU,TU,TU,TU,TU,TU,QR,ST,","(#f.d1.c2)[KL],#g2[KL],a2[KL],(#f.d1.c2)[KL],(g.d1.#a1)[KL],g2[KL],(c.c1.a1)[KL],#d2[KL],(d.#a.g1)[JM],a1[MN],g1[MN],(a.#f1)[KL],d1[KL],#a1[LM],d2[LM],(g1.#a2)[LM],d2[LM],(#f1.c2.a2)[LM],d2[LM],(g1.#a1.g2)[LM],d2[LM],(d1.c2.#f2)[LM],d2[LM],#c2[LM],d2[LM],e2[LM],#f2[LM],g2[LM],a2[LM],(#a1.#a2)[LM],d2[LM],(g1.#a2.d3)[LM],d2[LM],(#f1.a2.c3)[LM],d2[LM],(g1.g2.#a2)[LM],d2[LM],(f1.#d2.a2)[LM],f2[LM],e2[LM],f2[LM],g2[LM],a2[LM],#a2[LM],c3[LM],(#a1.d2.d3)[LM],f2[LM],(#a1.d3.f3)[LM],f2[LM],(a1.c3.#d3)[LM],f2[LM],(#a1.#a2.d3)[LM],f2[LM],(#f1.a2.c3)[LM],d2[LM],(g1.g2.#a2)[LM],d2[LM],(d1.#f2.a2)[LM],c2[LM],(#d1.g2)[LM],#a1[LM],c1[LM],a1[LM],#d2[LM],d2[LM],c2[LM],#a1[LM],(#c1.a1)[LM],g1[LM],(d1.#f1)[LM],g1[LM],a1[LM],#g1[LM],a1[LM],b1[LM],c2[LM],b1[LM],(#f.c2)[LM],d1[LM],(a.#f1)[LM],d1[LM],(c1.#f1)[LM],d1[LM],(a.#f1)[LM],d1[LM],(#a.g1)[LM],d1[MN],a1[N],g1[N],#f1[N],(g.g1)[LM],(d1.#a1)[LM],(#a.d2)[LM],d1[LM],(g.d2)[LM],d1[LM],(#f.c3)[LM],d1[LM],(a.#f2)[LM],d1[LM],(c1.#f2)[LM],d1[LM],(a.#f2)[LM],d1[LM],(#a.g2)[LM],d1[MN],a2[N],g2[N],#f2[N],(g.g2)[LM],(d1.#a2)[LM],(#a.d3)[LM],d1[LM],(g.d1)[LM],d1[LM],(#f.c2)[LM],d1[LM],(a.#f1)[LM],d1[LM],(c1.#f1)[LM],d1[LM],(a.#f1)[LM],d1[LM],(#a.g1)[LM],d1[MN],a1[N],g1[N],#f1[N],(g.g1)[LM],(d1.#a1)[LM],(f.b1)[LM],(d1.g1)[LM],(g.a1)[LM],(d1.b1)[LM],(#d.c2)[LM],c1[MN],d2[N],c2[N],b1[N],(g.c2)[LM],(c1.d2)[LM],(c.#d2)[LM],(g.f2)[LM],(#d.g2)[LM],(g.#d2)[LM],(#A-1.d2)[LM],g[LM],(d.#d2)[LM],(g.d2)[LM],(c.f2)[LM],(a.#d2)[LM],(#d.d2)[LM],(a.c2)[LM],(d.#a1)[LM],#a[LM],g[MN],c2[N],#a1[N],a1[N],(#a.#a1)[LM],(d.d2)[LM],(c1.c2)[LM],(#f.#a1)[LM],(c1.a1)[LM],(g.g1)[LM],d1[MN],a1[N],g1[N],#f1[N],(#a.g1)[LM],(d1.a1)[LM],(f.b1)[LM],(d1.g1)[LM],(g.a1)[LM],(d1.b1)[LM],(#d.c2)[LM],c1[MN],d2[N],c2[N],b1[N],(g.c2)[LM],(c1.d2)[LM],(c.#d2)[LM],(g.e2)[LM],(#d.f2)[LM],(g.#f2)[LM],(#c.g2)[LM],#a[LM],e[LM],#a[LM],g[LM],#a[MN],a2[N],g2[N],#f2[N],(e.g2)[LM],(#a.a2)[LM],(c.#a2)[LM],#a[LM],e[LM],#a[LM],(g.#c1)[LM],#a[LM],e[LM],#a[LM],(d.d1)[LM],d1[LM],(g.d2)[LM],d1[LM],#a[LM],d1[LM],(g.#c2)[LM],(d1.d2)[LM],(d.#d2)[LM],(d1.d2)[LM],(a.c2)[LM],(d1.#a1)[LM],(c1.a1)[LM],(d1.#a1)[LM],(a.c2)[LM],(d1.#f1)[LM],(d.g1)[LM],d1[LM],(g.g2)[LM],d1[LM],#a[LM],d1[LM],(g.#c2)[LM],(d1.d2)[LM],(d.#d2)[LM],(d1.d2)[LM],(a.c2)[LM],(d1.#a1)[LM],(c1.a1)[LM],(d1.#a1)[LM],(a.c2)[LM],(d1.#f1)[LM],(g.g1)[KL],(g.#a.d1)[KL],(g.#a.d1)[KL],(D-1.g.#a.d1)[KL],(c.a.c1.d1)[KL],(#F-1.a.c1.d1)[KL],(#F-1.a.c1.d1)[KL],(#F-1.a.c1.d1)[KL],(G-1.g1.g.#a)[KL],(g.#a.d1)[KL],(g.#a.d1)[KL],(D-1.g.#a.d1)[KL],(c.a.c1.d1)[KL],(#F-1.a.c1.d1)[KL],(#F-1.a.c1.d1)[KL],(#F-1.a.c1.d1)[KL],(G-1.g1.g.#a)[KL],(g.#a.d1)[KL],(g.#a.d1)[KL],(D-1.g.#a.d1)[KL],(c.a.c1.d1)[KL],(#F-1.a.c1.d1)[KL],(#F-1.a.c1.d1)[KL],(#F-1.a.c1.d1)[KL],(G-1.#a.d1)[KL],g[KL],(f1.b)[KL],g[KL],(G-2.#d1.c1)[KL],g[KL],(#d.c1)[KL],#f[KL],(G-1.d.b)[KL],g[KL],(f.d1)[KL],g[KL],(G-2.#d.c1)[KL],g[KL],(c.#f)[KL],#d[KL],(G-2.G-1.B-1.g)[KL],d[KL],(c.#f)[KL],#d[KL],(G-2.G-1.B-1.g)[KL],d[KL],(c.#f)[KL],#d[KL],(G-2.G-1.B-1.g)[KL],d[KL],(G-2.G-1.c.g)[KL],#d[KL],(G-2.G-1.B-1.g)[HI],ST,"],"id":3}],"audition":{"start":[0,0],"end":[1,0]}}