{"baseBpm":120,"musics":[{"id":1,"baseBeats":0.25,"scores":["g1[M],c1[M],d1[M],#d1[M],d1[M],c1[M];g1[M],c1[M],d1[M],#d1[M],d1[M],c1[M];g1[M],c1[M],d1[M],#d1[M],d1[M],c1[M];g1[M],c1[M],d1[M],#d1[M],d1[M],c1[M];g1[M],c1[M],d1[M],#d1[M],d1[M],c1[M];g1[M],c1[M],d1[M],#d1[M],d1[M],c1[M];f[M],c[M],d[M],#d[M],d[M],c[M];f[M],c[M],d[M],#d[M],d[M],c[M];g1[M],c1[M],d1[M],#d1[M],d1[M],c1[M];g1[M],c1[M],d1[M],#d1[M],d1[M],c1[M];g1[M],c1[M],d1[M],#d1[M],d1[M],c1[M];g1[M],c1[M],d1[M],#d1[M],d1[M],c1[M];#d2[M],#d1[M],#g1[M],#a1[M],#g1[M],#d1[M];b[M],#d[M],#g[M],#a[M],#g[M],#d[M];#a[M],#d[M],#g[M],#a[M],#g[M],#d[M];#a[M],#d[M],#g[M],#a[M],#g[M],#d[M];g1[M],c1[M],d1[M],#d1[M],d1[M],c1[M];g1[M],c1[M],d1[M],#d1[M],d1[M],c1[M];g1[M],c1[M],d1[M],#d1[M],d1[M],c1[M];#a1[M],c1[M],d1[M],#d1[M],d1[M],c1[M];#d1[M],g[M],#g[M],c1[M],#g[M],g[M];#d1[M],g[M],#g[M],c1[M],#g[M],g[M];#G-1[M],#g[M],#a[M],c1[M],#a[M],#g[M];G-1[M],c[M],d[M],#d[M],d[M],c[M];F-1[M],#g[M],c1[M],d1[M],c1[M],#g[M];F-1[M],#g[M],c1[M],d1[M],c1[M],#g[M];F-1[M],#g[M],c1[M],d1[M],c1[M],#g[M];G-1[M],g[M],c1[M],d1[M],c1[M],g[M];G-1[M],g[M],c1[M],d1[M],c1[M],g[M];G-1[M],g[M],c1[M],d1[M],c1[M],g[M];G-1[M],g[M],c1[M],d1[M],c1[M],g[M];(G-2.G-1)[M],g[M],c1[M],(g.d1)[M],c1[M],g[M];;","(g3.g4)[KN],(f3.f4)[MN],(#d3.#d4)[JLN],(d3.d4)[MN],(c3.c4)[MN],(#a2.#a3)[MN],(#g2.#g3)[MN],(g2.g3)[MN],(f2.f3)[KN],(g2.g3)[MN],(#d2.#d3)[KL],(c1.c2)[LM],(d1.d2)[LM],(#d1.#d2)[LM],(g2.g1)[LM],(g3.g4)[KN],(f3.f4)[MN],(#d3.#d4)[JLN],(d3.d4)[MN],(#d3.#d4)[MN],(d3.d4)[MN],(c3.c4)[MN],(g3.g4)[MN],(#g3.#g4)[KL],(b1.b2)[KL],(#a1.#a2)[KL],(#g1.#g2)[KL],(g3.g4)[KN],(f3.f4)[MN],(#d3.#d4)[JLN],(d3.d4)[MN],(c3.c4)[MN],(#a2.#a3)[MN],(#g2.#g3)[MN],(g2.g3)[MN],(f2.f3)[KN],(g2.g3)[MN],(#d2.#d3)[KL],(c1.c2)[LM],(d1.d2)[LM],(#d1.#d2)[LM],(g2.g1)[LM],(g3.g4)[KN],(f3.f4)[MN],(#d3.#d4)[JLN],(d3.d4)[MN],(#d3.#d4)[MN],(d3.d4)[MN],(c3.c4)[MN],(b2.b3)[MN],(c3.c4)[JL],(d3.d4)[M],(c3.c4)[M],(b2.b3)[KL],"]},{"id":2,"baseBeats":0.25,"scores":["(c@#d@g@c1)[M],c[M],d[M],#d[M],d[M],c[M];#d[M],c[M],d[M],#d[M],d[M],c[M];#d[M],c[M],d[M],#d[M],d[M],c[M];#d[M],c[M],d[M],#d[M],d[M],c[M];#d[M],c[M],d[M],#d[M],d[M],c[M];#d[M],c[M],d[M],#d[M],d[M],c[M];f[M],c[M],d[M],#d[M],d[M],c[M];f[M],c[M],d[M],#d[M],d[M],c[M];#d[M],c[M],d[M],#d[M],d[M],c[M];#d[M],c[M],d[M],#d[M],d[M],c[M];#d[M],c[M],d[M],#d[M],d[M],c[M];#d[M],c[M],d[M],#d[M],d[M],c[M];#A-1[M],#D-1[M],#G-1[M],#A-1[M],#G-1[M],#D-1[M];#A-1[M],#D-1[M],#G-1[M],#A-1[M],#G-1[M],#D-1[M];#A-1[M],#D-1[M],#G-1[M],#A-1[M],#G-1[M],#D-1[M];#A-1[M],#D-1[M],#G-1[M],#A-1[M],#G-1[M],#D-1[M];(#D-1.#F-1.#A-1)[M],#d[M],f[M],#f[M],f[M],#d[M];(#D-1.#F-1.#A-1)[M],#d[M],f[M],#f[M],f[M],#d[M];(#D-1.#F-1.#A-1)[M],#d[M],f[M],#f[M],f[M],#d[M];(#D-1.#F-1.#A-1)[M],#d[M],f[M],#f[M],f[M],#d[M];(B-2.#F-1.B-1)[M],#d[M],f[M],#f[M],f[M],#d[M];(B-2.#F-1.B-1)[M],#d[M],f[M],#f[M],f[M],(#D-1.#d)[M];(B-2.#F-1.B-1)[M],#d[M],f[M],#f[M],f[M],(#D-1.#d)[M];(B-2.#F-1.B-1)[M],#d[M],f[M],#f[M],f[M],#d[M];(#A-2.#A-1)[M],#a[M],#d1[M],f1[M],#d1[M],#a[M];(#A-2.#A-1)[M],#a[M],#d1[M],f1[M],#d1[M],#a[M];(B-2.B-1)[M],b[M],#d1[M],#f1[M],#d1[M],b[M];(B-2.B-1)[M],b[M],#d1[M],#f1[M],#d1[M],b[M];(#G-1.#g)[M],b[M],e1[M],#f1[M],e1[M],b[M];(#G-1.#g)[M],b[M],e1[M],#f1[M],e1[M],b[M];;","(c3.c4)[KN],(#d3.#d4)[MN],(d3.d4)[KN],(b2.b3)[MN],(c3.c4)[KN],(b2.b3)[MN],(c3.c4)[MN],(d3.d4)[MN],(#d3.#d4)[MN],(g3.g4)[MN],(#a3.#a4)[KN],(#g3.#g4)[MN],(g3.g4)[KN],(#d3.#d4)[MN],(c2.c3)[LM],(d2.f2.d3)[LM],(#d2.g2.#d3)[LM],(g2.c3.g3)[LM],(c3.c4)[KN],(#d3.#d4)[MN],(d3.d4)[KN],(b2.b3)[MN],(c3.c4)[KN],(b2.b3)[MN],(c3.c4)[MN],(d3.d4)[MN],(#d3.#d4)[MN],(g3.g4)[MN],(#a3.#a4)[KN],(b3.b4)[MN],(#g3.#g4)[KL],(#a2.#c3.#a3)[KL],(#g2.#c3.#g3)[KL],(#d3.#d4)[KN],(#f3.#f4)[MN],(f3.f4)[KN],(d3.d4)[MN],(#d3.#d4)[KN],(d3.d4)[MN],(#d3.#d4)[MN],(f3.f4)[MN],(#f3.#f4)[MN],(#a3.#a4)[MN],(#g3.#g4)[KN],(#a3.#a4)[MN],(#f3.#f4)[KL],(#f1.#f2)[LM],(f1.f2)[LM],(#f1.#f2)[LM],(#a1.#a2)[LM],(#a1.#a2)[KN],(#g1.#g2)[MN],(#a1.#a2)[JLN],(f3.f4)[MN],(#f3.#f4)[MN],(f3.f4)[MN],(#d3.#d4)[MN],(#a3.#a4)[MN],(b3.b4)[JLM],(#f1.#f2)[M],"]},{"id":3,"baseBeats":0.25,"scores":["G-1[M],b[M],d1[M],f1[M],d1[M],g[M];G-1[M],b[M],d1[M],f1[M],d1[M],b[M];#d[M],#G-1[M],#A-1[M],B-1[M],#A-1[M],#G-1[M];d[M],#G-1[M],#A-1[M],B-1[M],#A-1[M],#G-1[M];d[M],#G-1[M],#A-1[M],B-1[M],#A-1[M],#G-1[M];d[M],#G-1[M],#A-1[M],B-1[M],#A-1[M],#G-1[M];#d[M],#A-1[M],B-1[M],c[M],B-1[M],#A-1[M];#d[M],#A-1[M],B-1[M],c[M],B-1[M],#A-1[M];#d[M],#A-1[M],B-1[M],c[M],B-1[M],#A-1[M];#d[M],#A-1[M],B-1[M],c[M],B-1[M],#A-1[M];F-1[M],c1[M],#d1[M],#d1[M],d1[M],c1[M];F-1[M],c1[M],#d1[M],#d1[M],d1[M],c1[M];#D-1[M],#a[M],d1[M],d1[M],c1[M],#a[M];#D-1[M],#a[M],d1[M],d1[M],c1[M],#a[M];F-1[M],c1[M],#d1[M],#d1[M],d1[M],c1[M];F-1[M],c1[M],#d1[M],#d1[M],d1[M],c1[M];#d[M],#a[M],d1[M],d1[M],c1[M],#a[M];g[M],#g[M],#a[M],#a[M],#g[M],g[M];#G-1[M],#g[M],#a[M],c1[M],#a[M],#g[M];#G-1[M],#g[M],#a[M],c1[M],#a[M],#g[M];#G-1[M],#g[M],#a[M],V,#a[M],#g[M];#G-1[M],#g[M],#a[M],c1[M],#a[M],#g[M];#A-1[M],c1[M],d1[M],V,d1[M],c1[M];#A-1[M],c1[M],d1[M],#d1[M],d1[M],c1[M];#A-1[M],c1[M],d1[M],#d1[M],d1[M],c1[M];#A-1[M],c1[M],d1[M],#d1[M],d1[M],c1[M];(C-1.c)[M],#G-1[M],#A-1[M],c[M],#A-1[M],#G-1[M];(#D-1.#A-1.#d)[L],(D-1.#G-1.d)[L],(C-1.G-1.c)[L];(#A-2.#A-1)[M],G-1[M],#G-1[M],#A-1[M],#G-1[M],G-1[M];(#A-2.#A-1)[L],(F-2.F-1)[L],(#D-2.#D-1)[L];(#G-2.#G-1)[M],F-1[M],G-1[M],#G-1[M],G-1[M],F-1[M];(#A-2.F-1.#A-1)[L],(#A-2.F-1.#A-1)[L],(#A-2.F-1.#A-1)[L];(C-1.c)[LM],c[M],c[M],c[M];c[KL];(C-2.C-1)[KL];TU;","(g1.g2)[LM],(g1.g2)[LM];(g1.g2)[LM],(g1.g2)[LM];(c1.c2)[KN],(#d1.#d2)[MN];(d1.d2)[KN],(d1.d2)[MN];(c1.c2)[LM],(c1.c2)[M],(d1.d2)[M],(#d1.#d2)[M];(d1.d2)[LM],(#a.#a1)[LM];(#d1.#d2)[KN],(#d1.#d2)[MN];(d1.d2)[KN],(d1.d2)[MN];(c1.c2)[LM],(c1.c2)[M],(d1.d2)[M],(#d1.#d2)[M];(d1.d2)[LM],(#a.#a1)[LM];(#g1.#g2)[KN],(#g1.#g2)[MN];(#g1.#g2)[KN],(#d1.#d2)[MN];(g1.g2)[LM],(g1.g2)[M],(#g1.#g2)[M],(#a1.#a2)[M];(#g1.#g2)[LM],(g1.g2)[LM];(#g1.#g2)[KN],(#g1.#g2)[MN];(#g1.#g2)[KN],(#d1.#d2)[MN];(g1.g2)[LM],(g1.g2)[M],(#g1.#g2)[M],(#a1.#a2)[M];(#g1.#g2)[LM],(g1.g2)[LM];(#d1.#d2)[LM],(#d1.#d2)[M],(#d1.#d2)[M],(#d1.#d2)[M];(d1.d2)[LM],(d1.d2)[M],(d1.d2)[M],(d1.d2)[M];(c1.c2)[LM],(c1.c2)[M],(d1.d2)[M],(#d1.#d2)[M];(d1.d2)[LM],(#a.#a1)[LM];(#d1.#d2)[LM],(#d1.#d2)[M],(#d1.#d2)[M],(#d1.#d2)[M];(d1.d2)[LM],(d1.d2)[M],(d1.d2)[M],(d1.d2)[M];(c1.c2)[LM],(c1.c2)[M],(d1.d2)[M],(#d1.#d2)[M];(d1.d2)[LM],(#a.#a1)[LM];(g1.g2)[LM],(g1.g2)[M],(g1.g2)[M],(g1.g2)[M];(#a2.g2.#a2)[L],(#g1.f1.#g2)[L],(g1.#d2.g2)[L];(f1.#a1.f2)[LM],(f1.f2)[M],(g2.g1)[M],(#g1.#g2)[M];(g1.d2.g2)[L],(f1.#a1.f2)[L],(#d1.#g1.#d2)[L];(c1.#g1.c2)[LM],(c2.c1)[M],(d1.d2)[M],(#d1.#d2)[M];(d1.#a1.d2)[L],(d1.f1.d2)[L],(#a1.f1.#a2)[L];(c1.#d1.g1.c2)[L],(c1.#d1.g1.c2)[M],(c1.#d1.g1.c2)[M],(c1.#d1.g1.c2)[M];(c1.#d1.g1.c2)[JK];"]}],"audition":{"start":[0,0],"end":[0,20]}}